Workbook

Sheet 總覽
A1: FinFlow 財商沙盒 內容盤點
A2: 版本 v2.27.0-S22｜資料來源：github.com/briantsaivc-web/finflow 的 src/data/packs/*.json（11 個卡包）｜產出日期 2026-09-02
A3: 金額單位一律「千元」（月薪 30＝3 萬元；房子 1000＝100 萬元），與遊戲畫面顯示一致。每張工作表第 4 列為欄名，第 5 列起為資料，已開啟自動篩選。
A5: 工作表 | B5: 內容 | C5: 筆數（公式） | D5: 說明
A6: 職業 | B6: 20 種職業 | C6: =COUNTA(職業!A5:A24) -> 20 | D6: 20 種職業。金額單位＝千元／月（月薪 30＝3 萬）。「月結餘」為公式＝月薪−基本支出。
A7: 電腦玩家性格 | B7: 3 種 NPC 性格的決策權重（引擎 npc.* 直接讀這些值） | C7: =COUNTA(電腦玩家性格!A5:A7) -> 3 | D7: 3 種 NPC 性格的決策權重（引擎 npc.* 直接讀這些值）。現金保留水位＝月支出的倍數。
A8: 夢想 | B8: 8 張夢想卡（開局選一張作為最終目標；踩到對應類別的地點免費得點） | C8: =COUNTA(夢想!A5:A12) -> 8 | D8: 8 張夢想卡（開局選一張作為最終目標；踩到對應類別的地點免費得點）。
A9: 股票設定 | B9: 4 檔股票的股性參數（S15b 四層股價模型） | C9: =COUNTA(股票設定!A5:A8) -> 4 | D9: 4 檔股票的股性參數（S15b 四層股價模型）。面額單位＝千元／張。
A10: 股票掛單卡 | B10: ARCHIVED_STOCK：市場卡開出的掛單價（現行版本股票以股市面板交易，這批卡為封存內容） | C10: =COUNTA(股票掛單卡!A5:A14) -> 10 | D10: ARCHIVED_STOCK：市場卡開出的掛單價（現行版本股票以股市面板交易，這批卡為封存內容）。
A11: 機會卡 | B11: 小額 33／大額 25／特殊 8（特殊要有人脈才抽得到） | C11: =COUNTA(機會卡!A5:A70) -> 66 | D11: 小額 33／大額 25／特殊 8（特殊要有人脈才抽得到）。金額單位＝千元。「年化報酬率」為公式：事業＝月淨利×12÷價格；不動產＝(月租−月成本)×12÷價格；新創無現金流不算。吸金盤（isScam）到期整筆歸零。
A12: 人生事件卡 | B12: LIFE_EVENT（含二選一 CHOICE、自我投資 SELF_INVEST、獨立董事邀請 SPECIAL）＋ 職業事件 ＋ 夢想圈事件 OUTER_LIFE | C12: =COUNTA(人生事件卡!A5:A64) -> 60 | D12: LIFE_EVENT（含二選一 CHOICE、自我投資 SELF_INVEST、獨立董事邀請 SPECIAL）＋ 職業事件 ＋ 夢想圈事件 OUTER_LIFE。技能情境卡另列「學習-情境卡」。金額單位＝千元。
A13: 生活消費卡 | B13: LIFESTYLE 24 張：踩到生活格抽 | C13: =COUNTA(生活消費卡!A5:A28) -> 24 | D13: LIFESTYLE 24 張：踩到生活格抽。可選＝玩家可拒買；非可選＝直接扣款。金額單位＝千元。
A14: 市場與總經卡 | B14: MARKET 12 張（踩市場格）＋ MACRO_EVENT 20 張（景氣階段轉換時抽的政策／黑天鵝／台灣案例事件） | C14: =COUNTA(市場與總經卡!A5:A36) -> 32 | D14: MARKET 12 張（踩市場格）＋ MACRO_EVENT 20 張（景氣階段轉換時抽的政策／黑天鵝／台灣案例事件）。
A15: 品格帳本卡 | B15: LIFE_TAPESTRY 326 張（M6 品格帳本）：修養 CULTIVATE／考驗 TRIAL／日常 DAILY 等 | C15: =COUNTA(品格帳本卡!A5:A330) -> 326 | D15: LIFE_TAPESTRY 326 張（M6 品格帳本）：修養 CULTIVATE／考驗 TRIAL／日常 DAILY 等。每局抽樣 13＋13＋10。金額單位＝千元。
A16: 人生商城 | B16: MALL 26 件 | C16: =COUNTA(人生商城!A5:A30) -> 26 | D16: MALL 26 件。規則：只在自己回合買、每輪 1 件、同件 3 輪冷卻、重複購買幸福感遞減。「月薪倍數」有值者價格＝月薪×倍數（無薪時用固定價）。金額單位＝千元。
A17: 學習-技能 | B17: SKILL 18 種（M8） | C17: =COUNTA('學習-技能'!A5:A22) -> 18 | D17: SKILL 18 種（M8）。每局抽 6 張進場（抽到高階會把先修一起帶進來）。主動進修多花 1 輪；被動取得學費 7 折。金額單位＝千元。
A18: 學習-情境卡 | B18: SKILL_GATE 12 張：第 12 輪後出現，每局 5 張，只抽「對應技能本局有進場」的情境 | C18: =COUNTA('學習-情境卡'!A5:A16) -> 12 | D18: SKILL_GATE 12 張：第 12 輪後出現，每局 5 張，只抽「對應技能本局有進場」的情境。有技能兌現、沒有就錯過。
A19: 學習-數位資產 | B19: DIGITAL 6 種，每局 4 張，最多同時經營 3 個 | C19: =COUNTA('學習-數位資產'!A5:A10) -> 6 | D19: DIGITAL 6 種，每局 4 張，最多同時經營 3 個。有對應技能（或 AI 系統架構）＝專業：門檻 −1、爆紅 18%；沒有＝門檻 +2、爆紅 5%、50% 做白工。金額單位＝千元。
A20: 徽章 | B20: BADGE 29 種：復盤報告依 ns.badges.rules 的純函式判定 | C20: =COUNTA(徽章!A5:A33) -> 29 | D20: BADGE 29 種：復盤報告依 ns.badges.rules 的純函式判定。
A21: 盤面 | B21: 內圈 24 格＋外圈 12 格的格子類型 | C21: =COUNTA(盤面!A5:A40) -> 36 | D21: 內圈 24 格＋外圈 12 格的格子類型。
A22: 合計 | C22: =SUM(C6:C21) -> 680
A24: 牌堆對照（卡片類工作表包含的原始牌堆）：
A25: 機會卡 | B25: OPPORTUNITY_SMALL、OPPORTUNITY_LARGE、OPPORTUNITY_SPECIAL
A26: 人生事件卡 | B26: LIFE_EVENT（不含 SKILL_GATE）、PROFESSION_EVENT、OUTER_LIFE
A27: 生活消費卡 | B27: LIFESTYLE
A28: 市場與總經卡 | B28: MARKET、MACRO_EVENT
A29: 品格帳本卡 | B29: LIFE_TAPESTRY
A30: 人生商城 | B30: MALL
A31: 學習-技能／情境卡／數位資產 | B31: SKILL、LIFE_EVENT 中的 SKILL_GATE、DIGITAL
A32: 徽章 | B32: BADGE
A33: 夢想 | B33: DREAM
A34: 股票掛單卡 | B34: ARCHIVED_STOCK

Sheet 職業
A1: FinFlow 內容盤點｜職業
A2: 20 種職業。金額單位＝千元／月（月薪 30＝3 萬）。「月結餘」為公式＝月薪−基本支出。
A4: id | B4: 職業 | C4: 分類 | D4: 月薪 | E4: 基本月支出 | F4: 月結餘（公式） | G4: 每位小孩月支出 | H4: 起始現金 | I4: 起始負債 | J4: 起始資產 | K4: 薪資波動 | L4: 職業事件 | M4: 模組需求 | N4: 備註 | O4: 來源檔
A5: PRO_CLERK | B5: 超商正職店員 | C5: 服務 | D5: 30 | E5: 22 | F5: =D5-E5 -> 8 | G5: 8 | H5: 50 | K5: 0 | N5: 貼近基本工資的生存局 | O5: base.json
A6: PRO_FARMER | B6: 青農（承租務農） | C6: 農 | D6: 34 | E6: 20 | F6: =D6-E6 -> 14 | G6: 8 | H6: 60 | I6: 農機貸 本金 300｜年利率 0.015 | K6: 0.3 | N6: 看天吃飯；低支出是護城河 | O6: base.json
A7: PRO_TECHOP | B7: 工廠技術員 | C7: 工 | D7: 40 | E7: 25 | F7: =D7-E7 -> 15 | G7: 9 | H7: 100 | I7: 機車貸 本金 60｜年利率 0.045 | K7: 0 | N7: 穩定小盈餘，翻身靠紀律 | O7: base.json
A8: PRO_DELIVERY | B8: 外送員 | C8: 服務 | D8: 42 | E8: 24 | F8: =D8-E8 -> 18 | G8: 9 | H8: 80 | I8: 機車貸 本金 60｜年利率 0.045 | K8: 0.1 | N8: 低薪低支出，靠小額機會翻身 | O8: base.json
A9: PRO_MKT | B9: 行銷企劃專員 | C9: 商管 | D9: 42 | E9: 27 | F9: =D9-E9 -> 15 | G9: 10 | H9: 100 | I9: 學貸 本金 250｜年利率 0.018 | K9: 0 | N9: BBA 最大宗出路 | O9: base.json
A10: PRO_AUDITOR | B10: 四大事務所查帳員 | C10: 商管 | D10: 48 | E10: 28 | F10: =D10-E10 -> 20 | G10: 10 | H10: 120 | I10: 學貸 本金 300｜年利率 0.018 | K10: 0 | L10: PE_CPA_EXAM | N10: 考照可跳級加薪 40% | O10: base.json
A11: PRO_NURSE | B11: 護理師 | C11: 醫療 | D11: 55 | E11: 30 | F11: =D11-E11 -> 25 | G11: 10 | H11: 200 | I11: 學貸 本金 200｜年利率 0.018 | K11: 0 | N11: 均衡入門 | O11: base.json
A12: PRO_CIVIL | B12: 公務員 | C12: 服務 | D12: 58 | E12: 32 | F12: =D12-E12 -> 26 | G12: 10 | H12: 350 | K12: 0 | N12: 穩定但天花板低 | O12: base.json
A13: PRO_BANKER | B13: 銀行理專 | C13: 商管 | D13: 58 | E13: 34 | F13: =D13-E13 -> 24 | G13: 11 | H13: 200 | I13: 學貸 本金 200｜年利率 0.018 | K13: 0.25 | N13: 底薪加佣金，先體驗浮動收入 | O13: base.json
A14: PRO_PLUMBER | B14: 水電師傅（自營） | C14: 工 | D14: 65 | E14: 35 | F14: =D14-E14 -> 30 | G14: 11 | H14: 250 | I14: 工程車貸 本金 400｜年利率 0.035 | K14: 0.25 | N14: 接案制，無雇主退休金 | O14: base.json
A15: PRO_DATA | B15: 資料分析師 | C15: 商管 | D15: 68 | E15: 36 | F15: =D15-E15 -> 32 | G15: 11 | H15: 300 | I15: 學貸 本金 300｜年利率 0.018 | K15: 0 | N15: 程式與商管的交集 | O15: base.json
A16: PRO_ECOM | B16: 電商營運經理 | C16: 商管 | D16: 72 | E16: 42 | F16: =D16-E16 -> 30 | G16: 12 | H16: 250 | I16: 學貸 本金 250｜年利率 0.018 | K16: 0.15 | N16: 旺季獎金淡季平 | O16: base.json
A17: PRO_ENGINEER | B17: 軟體工程師 | C17: 科技 | D17: 75 | E17: 38 | F17: =D17-E17 -> 37 | G17: 12 | H17: 400 | I17: 學貸 本金 300｜年利率 0.018 | K17: 0 | N17: 標準局 | O17: base.json
A18: PRO_FOOD | B18: 小吃店老闆 | C18: 商 | D18: 80 | E18: 45 | F18: =D18-E18 -> 35 | G18: 12 | H18: 150 | I18: 創業貸 本金 800｜年利率 0.025 | K18: 0.2 | N18: 休息就沒有收入 | O18: base.json
A19: PRO_SALES | B19: 業務經理 | C19: 商 | D19: 90 | E19: 55 | F19: =D19-E19 -> 35 | G19: 13 | H19: 300 | I19: 車貸 本金 500｜年利率 0.035；信用卡循環 本金 100｜年利率 0.15 | K19: 0.15 | N19: 高薪高支出的陷阱教材 | O19: base.json
A20: PRO_PM | B20: 產品經理 | C20: 商管 | D20: 95 | E20: 52 | F20: =D20-E20 -> 43 | G20: 14 | H20: 400 | I20: 學貸與在職進修貸 本金 350｜年利率 0.018 | K20: 0 | N20: 程式與管理的交集 | O20: base.json
A21: PRO_SEMI | B21: 半導體工程師 | C21: 科技 | D21: 110 | E21: 48 | F21: =D21-E21 -> 62 | G21: 14 | H21: 500 | I21: 學貸 本金 300｜年利率 0.018 | K21: 0 | L21: PE_SEMI_BONUS | N21: 年終分紅是存量不是流量 | O21: base.json
A22: PRO_CONSULT | B22: 外商管理顧問 | C22: 商管 | D22: 165 | E22: 92 | F22: =D22-E22 -> 73 | G22: 18 | H22: 500 | I22: MBA 留學貸 本金 1500｜年利率 0.032 | K22: 0 | N22: 開局淨值為負：高薪先還債 | O22: base.json
A23: PRO_FOUNDER | B23: 新創創辦人 | C23: 商管 | D23: 36 | E23: 30 | F23: =D23-E23 -> 6 | G23: 10 | H23: 150 | I23: 創業貸 本金 600｜年利率 0.025 | J23: [{"kind": "STARTUP", "cardId": "OWN_STARTUP", "name": "我的公司", "costBasis": 0, "marketValue": 1500, "equityPct": 0.3, "postMoney": 5000, "monthlyIncome": 0, "flags": {"isOwnCompany": true}}] | K23: 0.2 | M23: M3 | N23: 薪水最低，但持有自己公司三成股權 | O23: base.json
A24: PRO_DOCTOR | B24: 主治醫師 | C24: 醫療 | D24: 280 | E24: 165 | F24: =D24-E24 -> 115 | G24: 25 | H24: 800 | I24: 學貸 本金 800｜年利率 0.018；自住宅房貸 本金 12000｜年利率 0.022｜機動 | K24: 0 | N24: 自住宅不入資產欄，只留負債與月付息 | O24: base.json
A26: 合計／平均 | D26: =AVERAGE(D5:D24) -> 77.15 | E26: =AVERAGE(E5:E24) -> 44 | F26: =AVERAGE(F5:F24) -> 33.15 | H26: =AVERAGE(H5:H24) -> 263
A27: 註：合計列為平均值（公式）。

Sheet 電腦玩家性格
A1: FinFlow 內容盤點｜電腦玩家性格
A2: 3 種 NPC 性格的決策權重（引擎 npc.* 直接讀這些值）。現金保留水位＝月支出的倍數。
A4: id | B4: 名稱 | C4: 顏色 | D4: 現金保留水位（×月支出） | E4: 貸款成數上限 | F4: 現金流/成本權重 | G4: 資本利得偏好 | H4: 新創偏好 | I4: 買享樂卡機率 | J4: 修品格機率 | K4: 來源檔
A5: NPC_SAFE | B5: 穩健阿姨 | C5: #35C4A8 | D5: 6 | E5: 0.4 | F5: 1 | G5: 0.2 | H5: 0 | I5: 0.1 | J5: 0.85 | K5: base.json
A6: NPC_LEVER | B6: 槓桿哥 | C6: #F0803C | D6: 1.5 | E6: 0.85 | F6: 1.4 | G6: 0.6 | H6: 0.3 | I6: 0.45 | J6: 0.15 | K6: base.json
A7: NPC_VC | B7: 風投弟 | C7: #B45FD0 | D7: 1 | E7: 0.7 | F7: 0.5 | G7: 1.3 | H7: 1.5 | I7: 0.3 | J7: 0.4 | K7: base.json

Sheet 夢想
A1: FinFlow 內容盤點｜夢想
A2: 8 張夢想卡（開局選一張作為最終目標；踩到對應類別的地點免費得點）。
A4: id | B4: 夢想 | C4: 類別 | D4: 單位敘述 | E4: 完成敘述 | F4: 每月維持費 | G4: 情境 | H4: 里程碑 | I4: 標籤 | J4: 來源檔
A5: DREAM_STARS | B5: 摘下二十顆米其林星 | C5: TASTE | D5: 顆星 | E5: 20 | F5: 15 | G5: 把味覺的記憶排成一條銀河。 | H5: ["東京・鮨 さいとう：第 1 顆星入袋", "巴斯克海岸・Asador Etxebarri：柴燒的極致", "香港・大班樓：花雕蒸蟹的那一夜", "哥本哈根・Geranium：北歐的森林上桌", "台北・態芮：最後四顆星，圓滿二十"] | I5: food | J5: base.json
A6: DREAM_SHOPS | B6: 環島吃遍一百家老店 | C6: TASTE | D6: 家 | E6: 100 | F6: 15 | G6: 每一碗湯裡都有一個小鎮。 | H6: ["台南・阿堂鹹粥：清晨五點的第一碗", "鹿港・肉包子店：排了四十分鐘", "嘉義・噴水雞肉飯：兩碗才夠", "宜蘭・正好鮮肉小籠包：出爐即秒殺", "基隆廟口・天婦羅：第一百家，環島收官"] | I6: food | J6: base.json
A7: DREAM_PEAKS | B7: 完登台灣百岳 | C7: SUMMIT | D7: 座 | E7: 100 | F7: 15 | G7: 把台灣的稜線走成自己的年輪。 | H7: ["玉山主峰 3,952m：台灣最高點", "雪山東峰＋主峰：黑森林裡的一夜", "大霸尖山：世紀奇峰就在眼前", "南湖大山：帝王之山的圈谷", "北大武山：百岳最後一座，南台灣的雲海"] | I7: outdoor | J7: base.json
A8: DREAM_DIVE | B8: 潛遍世界十大潛點 | C8: SUMMIT | D8: 處 | E8: 10 | F8: 15 | G8: 海面下沒有時間。 | H8: ["帛琉・藍角：鯊魚順著流一起飛", "埃及・紅海 SS Thistlegorm 沉船", "墨西哥・Cenote 天井洞穴：光柱穿透", "印尼・Raja Ampat：全世界魚最多的海", "澳洲・大堡礁：第十處，海面下的告別"] | I8: outdoor | J8: base.json
A9: DREAM_CONTINENT | B9: 七大洲都留下腳印 | C9: VOYAGE | D9: 洲 | E9: 7 | F9: 15 | G9: 地圖上還有空白的地方。 | H9: ["亞洲・尼泊爾 ABC 基地營", "歐洲・冰島環島一號公路", "非洲・坦尚尼亞塞倫蓋提大遷徙", "美洲・巴塔哥尼亞百內 W 健行", "南極・跨越德瑞克海峽登陸，七大洲完成"] | I9: travel | J9: base.json
A10: DREAM_SAIL | B10: 駕帆船橫越太平洋 | C10: VOYAGE | D10: 段航程 | E10: 5 | F10: 15 | G10: 風會告訴你今天要去哪裡。 | H10: ["第 1 段：高雄－沖繩，第一次獨自守夜", "第 2 段：沖繩－關島，遇上第一場風暴", "第 3 段：關島－馬紹爾，無風帶的三天", "第 4 段：馬紹爾－夏威夷，信風終於來了", "第 5 段：夏威夷－舊金山，橫越太平洋完成"] | I10: travel | J10: base.json
A11: DREAM_SCHOOL | B11: 創辦一所實驗學校 | C11: LEGACY | D11: 個里程碑 | E11: 5 | F11: 15 | G11: 你想給孩子的，是你當年沒有的。 | H11: ["第 1 個里程碑：租下廢棄校舍，簽下十年約", "第 2 個里程碑：第一批 12 位學生報到", "第 3 個里程碑：自編課綱通過實驗教育審議", "第 4 個里程碑：第一屆畢業生升學放榜", "第 5 個里程碑：學校自負盈虧，不再需要你補貼"] | I11: legacy | J11: base.json
A12: DREAM_FOUND | B12: 成立家族公益基金會 | C12: LEGACY | D12: 個計畫 | E12: 10 | F12: 15 | G12: 錢最後會變成什麼，由你決定。 | H12: ["第 1 個計畫：偏鄉課輔據點開張", "第 2 個計畫：清寒學生獎學金首度發放", "第 3 個計畫：食物銀行與在地小農合作", "第 4 個計畫：長者共餐據點滿一年", "第 5 個計畫：基金會孳息可自養，永續運作"] | I12: legacy | J12: base.json

Sheet 股票設定
A1: FinFlow 內容盤點｜股票設定
A2: 4 檔股票的股性參數（S15b 四層股價模型）。面額單位＝千元／張。
A4: 代號 | B4: 名稱 | C4: 面額 | D4: 月股息率 | E4: 波動 | F4: 景氣 beta | G4: 單輪最大漲跌 | H4: 漂移加成 | I4: 景氣說明 | J4: 股性說明 | K4: 來源檔
A5: STK_TECH | B5: 晶宇科技（成長股） | C5: 45 | D5: 0 | E5: 0.075 | F5: 1.4 | G5: 0.25 | H5: 0.004 | I5: 對景氣敏感（約大盤的 1.4 倍） | J5: 押的是未來的獲利，不是現在的配息。景氣好時漲得比大盤凶，景氣一轉也跌得比大盤快；不配息，報酬全靠價差。 | K5: base.json
A6: STK_DIV | B6: 台興電信（高股息） | C6: 28 | D6: 0.004 | E6: 0.028 | F6: 0.5 | G6: 0.12 | H6: -0.001 | I6: 對景氣不敏感（約大盤的 0.5 倍） | J6: 成熟產業、現金流穩，每月都配息。漲的時候跟不上別人，但崩盤時是全場跌最少的——防禦力就是它的報酬。 | K6: base.json
A7: STK_ETF | B7: 寶島大盤 ETF | C7: 60 | D7: 0.0022 | E7: 0.045 | F7: 1 | G7: 0.18 | H7: 0 | I7: 就是大盤（1 倍） | J7: 一次買一籃子，漲跌就是大盤本身。不會讓你一夕致富，也不會讓你一夕歸零——是拿來當基準的那一檔。 | K7: base.json
A8: STK_SPEC | B8: 星火小型股（投機） | C8: 12 | D8: 0 | E8: 0.105 | F8: 1.8 | G8: 0.3 | H8: 0.006 | I8: 對景氣極度敏感（約大盤的 1.8 倍） | J8: 小型股，題材一來就飛、消息一散就崩，不配息。景氣好時最會漲，蕭條時跌最深，而且是全場唯一可能下市歸零的一檔。 | K8: base.json

Sheet 股票掛單卡
A1: FinFlow 內容盤點｜股票掛單卡
A2: ARCHIVED_STOCK：市場卡開出的掛單價（現行版本股票以股市面板交易，這批卡為封存內容）。
A4: id | B4: 標題 | C4: 代號 | D4: 掛單價 | E4: 最少張數 | F4: 最多張數 | G4: 情境 | H4: 教育註記 | I4: 標籤 | J4: 模組 | K4: 來源檔
A5: OPS_ST1 | B5: 晶宇科技 開盤掛單 | C5: STK_TECH | D5: 43 | E5: 1 | F5: 9999 | G5: 法人連三天買超。 | H5: 成長股不配息，你賺的是價差；價差沒實現前都只是紙上富貴。 | I5: equity | K5: base.json
A6: OPS_ST2 | B6: 台興電信 除息前買點 | C6: STK_DIV | D6: 27 | E6: 1 | F6: 9999 | G6: 殖利率剛好落在近五年高點。 | H6: 高股息股每月配息會直接變成你的被動收入。 | I6: equity、dividend | K6: base.json
A7: OPS_ST3 | B7: 寶島大盤 ETF 定期買 | C7: STK_ETF | D7: 58 | E7: 1 | F7: 9999 | G7: 不用選股，買下整個市場。 | H7: ETF 用分散換掉個股風險，代價是你也拿不到暴賺。 | I7: equity | K7: base.json
A8: OPS_ST4 | B8: 星火小型股 消息面 | C8: STK_SPEC | D8: 9 | E8: 1 | F8: 9999 | G8: 群組裡都在喊，據說有大單。 | H8: 聽消息買股票不是投資，是猜拳；它的波動是大盤的四倍。 | I8: equity、speculative | K8: base.json
A9: OPS_ST5 | B9: 台興電信 回檔加碼 | C9: STK_DIV | D9: 24 | E9: 1 | F9: 9999 | G9: 跌了兩成，殖利率更漂亮了。 | H9: 同一檔股票在不同價格買，殖利率完全不同。 | I9: equity、dividend | K9: base.json
A10: OPS_ST6 | B10: 晶宇科技 追高 | C10: STK_TECH | D10: 52 | E10: 1 | F10: 9999 | G10: 新聞說要進蘋果供應鏈。 | H10: 追在高點的成本會跟著你很久，成本價決定你的報酬率。 | I10: equity | K10: base.json
A11: OPS_ST7 | B11: 晶宇科技 法說會後 | C11: STK_TECH | D11: 43 | E11: 1 | F11: 9999 | G11: 財測上修，但股價已經先漲了一段。 | H11: 好消息公布時，價格常常已經反映完了——這叫「利多出盡」。 | I11: equity | K11: v10.json
A12: OPS_ST8 | B12: 台興電信 定期定額 | C12: STK_DIV | D12: 27 | E12: 1 | F12: 9999 | G12: 每個月固定扣款，不看盤。 | H12: 定期定額是用紀律換掉擇時：你不會買在最低，但也不會全押在最高。 | I12: equity、dividend | K12: v10.json
A13: OPS_ST9 | B13: 寶島大盤 ETF 逢低加碼 | C13: STK_ETF | D13: 58 | E13: 1 | F13: 9999 | G13: 大盤回檔一成，你手上剛好有現金。 | H13: 能在下跌時加碼的人，靠的不是勇氣，是平時留的現金。 | I13: equity | K13: v10.json
A14: OPS_ST10 | B14: 星火小型股 群組明牌 | C14: STK_SPEC | D14: 11 | E14: 1 | F14: 9999 | G14: 群組裡的人說「這支要噴了」。 | H14: 聽明牌買進的人，通常也會聽明牌賣出——而那個人不會通知你。 | I14: equity、speculative | K14: v10.json

Sheet 機會卡
A1: FinFlow 內容盤點｜機會卡
A2: 小額 33／大額 25／特殊 8（特殊要有人脈才抽得到）。金額單位＝千元。「年化報酬率」為公式：事業＝月淨利×12÷價格；不動產＝(月租−月成本)×12÷價格；新創無現金流不算。吸金盤（isScam）到期整筆歸零。
A4: 牌堆 | B4: id | C4: 類型 | D4: 標題 | E4: 價格 | F4: 自備款 | G4: 月租金 | H4: 月成本 | I4: 月淨利 | J4: 年化報酬率（公式） | K4: 投資額（新創） | L4: 股權% | M4: 投後估值 | N4: 房貸利率 | O4: 機動利率 | P4: 出場倍數 | Q4: 淨利波動 | R4: 吸金盤 | S4: 爆雷輪數 | T4: 中階標的 | U4: 分組 | V4: 階段 | W4: 情境 | X4: 教育註記 | Y4: 標籤 | Z4: 模組 | AA4: 來源檔
A5: OPPORTUNITY_SMALL | B5: OPS_MICRO1 | C5: REALESTATE | D5: 社區停車位一席 | E5: 420 | F5: 84 | G5: 3.5 | H5: 0.3 | J5: =IF(AND(ISNUMBER(E5),E5>0),(N(G5)-N(H5))*12/E5,"") -> 0.091428571 | N5: 0.026 | O5: 是 | P5: {"RECOVERY": 1.0, "BOOM": 1.2, "RECESSION": 0.92, "DEPRESSION": 0.75} | W5: 車位比車還保值，至少不會拋錨。 | X5: 用小額自備款控制一個會生租金的資產，這就是槓桿的入門。 | Y5: housing | AA5: base.json
A6: OPPORTUNITY_SMALL | B6: OPS_MICRO2 | C6: REALESTATE | D6: 老公寓分租一房 | E6: 850 | F6: 170 | G6: 8 | H6: 1 | J6: =IF(AND(ISNUMBER(E6),E6>0),(N(G6)-N(H6))*12/E6,"") -> 0.098823529 | N6: 0.024 | O6: 是 | P6: {"RECOVERY": 1.0, "BOOM": 1.22, "RECESSION": 0.9, "DEPRESSION": 0.7} | W6: 押一付二，房客是隔壁大學的研究生。 | X6: 低總價的分租，讓小資族也能踏出第一步。 | Y6: housing | AA6: base.json
A7: OPPORTUNITY_SMALL | B7: OPS_MICRO3 | C7: BUSINESS | D7: 自動販賣機兩台 | E7: 90 | I7: 3.5 | J7: =IF(AND(ISNUMBER(E7),E7>0,ISNUMBER(I7)),I7*12/E7,"") -> 0.46666667 | Q7: 是 | W7: 擺在辦公大樓一樓，飲料補貨自己來。 | X7: 小額起步的現金流，賺的不多但立刻開始複利。 | Y7: business | AA7: base.json
A8: OPPORTUNITY_SMALL | B8: OPS_MICRO4 | C8: BUSINESS | D8: 網拍庫存轉售 | E8: 60 | I8: 2.6 | J8: =IF(AND(ISNUMBER(E8),E8>0,ISNUMBER(I8)),I8*12/E8,"") -> 0.52 | Q8: 是 | W8: 一批換季出清的球鞋，賭它翻倍。 | X8: 最低門檻的小生意，適合當第一桶金的起點。 | Y8: business | AA8: base.json
A9: OPPORTUNITY_SMALL | B9: OPS_RE1 | C9: REALESTATE | D9: 三重公寓隔套收租 | E9: 2200 | F9: 440 | G9: 16 | H9: 3 | J9: =IF(AND(ISNUMBER(E9),E9>0),(N(G9)-N(H9))*12/E9,"") -> 0.070909091 | N9: 0.0235 | O9: 是 | P9: {"RECOVERY": 1.0, "BOOM": 1.3, "RECESSION": 0.85, "DEPRESSION": 0.62} | W9: 屋主移民急售，已隔三套滿租。 | X9: 頭期款進資產欄、貸款進負債欄；租金減掉支出與利息，剩下的才是你的現金流。 | Y9: housing、leverage | AA9: base.json
A10: OPPORTUNITY_SMALL | B10: OPS_RE2 | C10: REALESTATE | D10: 中壢學區套房 | E10: 1600 | F10: 320 | G10: 13 | H10: 2 | J10: =IF(AND(ISNUMBER(E10),E10>0),(N(G10)-N(H10))*12/E10,"") -> 0.0825 | N10: 0.022 | O10: 是 | P10: {"RECOVERY": 1.0, "BOOM": 1.25, "RECESSION": 0.88, "DEPRESSION": 0.65} | W10: 對面就是大學側門，寒暑假空租兩個月。 | X10: 空置率是隱形成本，看報酬率時要先扣掉它。 | Y10: housing | AA10: base.json
A11: OPPORTUNITY_SMALL | B11: OPS_RE3 | C11: REALESTATE | D11: 高雄鹽埕老公寓 | E11: 1200 | F11: 240 | G11: 11 | H11: 2 | J11: =IF(AND(ISNUMBER(E11),E11>0),(N(G11)-N(H11))*12/E11,"") -> 0.09 | N11: 0.024 | O11: 是 | P11: {"RECOVERY": 1.0, "BOOM": 1.22, "RECESSION": 0.9, "DEPRESSION": 0.68} | W11: 屋齡四十年，但巷口就是輕軌站。 | X11: 老屋維修費會吃掉現金流，買前先問修繕準備金。 | Y11: housing | AA11: base.json
A12: OPPORTUNITY_SMALL | B12: OPS_RE4 | C12: REALESTATE | D12: 桃園小坪數廠辦 | E12: 2400 | F12: 480 | G12: 19 | H12: 4 | J12: =IF(AND(ISNUMBER(E12),E12>0),(N(G12)-N(H12))*12/E12,"") -> 0.075 | N12: 0.026 | O12: 是 | P12: {"RECOVERY": 1.0, "BOOM": 1.28, "RECESSION": 0.82, "DEPRESSION": 0.6} | W12: 承租戶是做模具的老師傅，一租十年。 | X12: 長約租客降低空置風險，這也是一種報酬。 | Y12: housing、commercial | AA12: base.json
A13: OPPORTUNITY_SMALL | B13: OPS_BZ1 | C13: BUSINESS | D13: 自助洗衣店（頂讓） | E13: 380 | I13: 13 | J13: =IF(AND(ISNUMBER(E13),E13>0,ISNUMBER(I13)),I13*12/E13,"") -> 0.41052632 | Q13: 否 | W13: 機器五成新，社區人口穩定。 | X13: 事業要全額現金買下，沒有槓桿；但它的現金流不用等房客。 | Y13: business | AA13: base.json
A14: OPPORTUNITY_SMALL | B14: OPS_BZ2 | C14: BUSINESS | D14: 手搖飲加盟店 | E14: 400 | I14: 15 | J14: =IF(AND(ISNUMBER(E14),E14>0,ISNUMBER(I14)),I14*12/E14,"") -> 0.45 | Q14: 是 | W14: 品牌方保證帶客，權利金另計。 | X14: 加盟等於買現成系統，但你的利潤要分給品牌。 | Y14: business | AA14: base.json
A15: OPPORTUNITY_SMALL | B15: OPS_BZ3 | C15: BUSINESS | D15: 夾娃娃機三台 | E15: 120 | I15: 4.5 | J15: =IF(AND(ISNUMBER(E15),E15>0,ISNUMBER(I15)),I15*12/E15,"") -> 0.45 | Q15: 是 | W15: 就放在夜市入口。 | X15: 小額但高波動，適合當第一個現金流實驗。 | Y15: business | AA15: base.json
A16: OPPORTUNITY_SMALL | B16: OPS_BZ4 | C16: BUSINESS | D16: 校園販賣機組 | E16: 260 | I16: 9 | J16: =IF(AND(ISNUMBER(E16),E16>0,ISNUMBER(I16)),I16*12/E16,"") -> 0.41538462 | Q16: 否 | W16: 跟學校簽三年約。 | X16: 有約在身的收入比較好預測，這就是現金流品質。 | Y16: business | AA16: base.json
A17: OPPORTUNITY_SMALL | B17: OPS_SU1 | C17: STARTUP | D17: 朋友的外送機器人團隊（種子輪） | K17: 280 | L17: 0.06 | M17: 4600 | W17: 三個人、一間車庫、一台改裝的推車。 | X17: 種子輪投的是人，不是財報——因為那時候還沒有財報。 | Z17: M3 | AA17: base.json
A18: OPPORTUNITY_SMALL | B18: OPS_SU2 | C18: STARTUP | D18: 寵物保健食品品牌（天使輪） | K18: 360 | L18: 0.07 | M18: 5100 | W18: 創辦人自己的狗吃了兩年，才敢拿出來賣。 | X18: 小額參與可以買到經驗，但別把它當成分散——一次投一家不叫分散。 | Z18: M3 | AA18: base.json
A19: OPPORTUNITY_SMALL | B19: OPS_SU3 | C19: STARTUP | D19: 在地食材冷鏈平台（Pre-A） | K19: 520 | L19: 0.08 | M19: 6500 | W19: 已經有三家餐廳在用，但還在燒錢。 | X19: 有營收不等於會賺錢；燒錢速度才決定它撐得到下一輪嗎。 | Z19: M3 | AA19: base.json
A20: OPPORTUNITY_SMALL | B20: OPP_HONGYUAN_FUND | C20: BUSINESS | D20: 封閉型民間高息專案 | E20: 100 | F20: 100 | I20: 4.5 | J20: =IF(AND(ISNUMBER(E20),E20>0,ISNUMBER(I20)),I20*12/E20,"") -> 0.54 | R20: 是 | S20: 3 | U20: 高息投資 | V20: INNER | W20: 鄰居每個月都在領 4.5% 利息，介紹人拍胸脯保證絕對穩當，名額只剩這週！ | X20: 你貪他的高利息，他要你的全家本金。世上沒有年化 30% 還保本的生意（歷史原型：鴻源吸金案）。 | AA20: base.json
A21: OPPORTUNITY_SMALL | B21: OPP_GOLD_REPURCHASE | C21: BUSINESS | D21: 實體黃金保本回購專案 | E21: 150 | F21: 150 | I21: 6 | J21: =IF(AND(ISNUMBER(E21),E21>0,ISNUMBER(I21)),I21*12/E21,"") -> 0.48 | R21: 是 | S21: 4 | U21: 黃金貴金屬 | V21: INNER | W21: 業務把沉甸甸的金條擺在眼前，合約白紙黑字寫著保證原價買回、每月加贈 4% 利息。 | X21: 『保本』與『高於定存數倍的利息』在財務物理學上是互相矛盾的（歷史原型：聖石金業案）。 | AA21: base.json
A22: OPPORTUNITY_SMALL | B22: OPP_RED_SLIP_HOUSING | C22: REALESTATE | D22: 預售屋紅單轉手套利 | E22: 1000 | F22: 100 | G22: 0 | H22: 1.5 | J22: =IF(AND(ISNUMBER(E22),E22>0),(N(G22)-N(H22))*12/E22,"") -> -0.018 | U22: 房地產 | V22: INNER | W22: 房仲低聲說：現在買紅單卡位，等開盤轉約現賺，根本不用真的交屋。 | X22: 預售屋槓桿是雙面刃；一旦政策收緊禁止轉約或限貸，繳不出尾款便是全額違約沒收。 | AA22: base.json
A23: OPPORTUNITY_SMALL | B23: OPS_BZ5 | C23: BUSINESS | D23: 夜市小吃攤（頂讓） | E23: 150 | I23: 5.4 | J23: =IF(AND(ISNUMBER(E23),E23>0,ISNUMBER(I23)),I23*12/E23,"") -> 0.432 | Q23: 是 | W23: 人潮＝現金流，但攤位租約只剩兩年。 | X23: 生意好壞先看「來客數 × 客單價」，再看你要付出多少工時。 | Y23: business | AA23: v10.json
A24: OPPORTUNITY_SMALL | B24: OPS_BZ6 | C24: BUSINESS | D24: 社區自助洗車機 | E24: 200 | I24: 7 | J24: =IF(AND(ISNUMBER(E24),E24>0,ISNUMBER(I24)),I24*12/E24,"") -> 0.42 | W24: 投幣式、無人顧，週末排隊。 | X24: 設備型生意的重點是折舊與故障率，別只看月營收。 | Y24: business | AA24: v10.json
A25: OPPORTUNITY_SMALL | B25: OPS_BZ8 | C25: BUSINESS | D25: 寵物美容工作室 | E25: 320 | I25: 11 | J25: =IF(AND(ISNUMBER(E25),E25>0,ISNUMBER(I25)),I25*12/E25,"") -> 0.4125 | Q25: 是 | W25: 老客戶回訪率高，但很吃師傅。 | X25: 依賴特定人力的生意，人一走現金流就斷——這叫關鍵人風險。 | Y25: business | AA25: v10.json
A26: OPPORTUNITY_SMALL | B26: OPS_BZ10 | C26: BUSINESS | D26: 共享機車充電站 | E26: 240 | I26: 8.4 | J26: =IF(AND(ISNUMBER(E26),E26>0,ISNUMBER(I26)),I26*12/E26,"") -> 0.42 | W26: 跟里長談好三個車位。 | X26: 政策紅利型生意：補助在時很甜，補助沒了要能自己活。 | Y26: business | AA26: v10.json
A27: OPPORTUNITY_SMALL | B27: OPS_RE5 | C27: REALESTATE | D27: 台南巷弄一樓店面 | E27: 1900 | F27: 380 | G27: 15 | H27: 1.8 | J27: =IF(AND(ISNUMBER(E27),E27>0),(N(G27)-N(H27))*12/E27,"") -> 0.083368421 | W27: 觀光客會走到，房東要移民。 | X27: 店面收益看的是「租客賺不賺錢」，租客倒了你就空租。 | Y27: housing、commercial | AA27: v10.json
A28: OPPORTUNITY_SMALL | B28: OPS_RE6 | C28: REALESTATE | D28: 基隆港邊小套房 | E28: 980 | F28: 196 | G28: 8.5 | H28: 1 | J28: =IF(AND(ISNUMBER(E28),E28>0),(N(G28)-N(H28))*12/E28,"") -> 0.091836735 | W28: 海景第一排，也是潮濕第一排。 | X28: 便宜通常有原因：維護成本與空租率要先算進去。 | Y28: housing | AA28: v10.json
A29: OPPORTUNITY_SMALL | B29: OPS_RE7 | C29: REALESTATE | D29: 新莊工業宅兩房 | E29: 1350 | F29: 405 | G29: 11 | H29: 1.3 | J29: =IF(AND(ISNUMBER(E29),E29>0),(N(G29)-N(H29))*12/E29,"") -> 0.086222222 | W29: 總價漂亮，但不能設戶籍、貸款成數低。 | X29: 權狀用途會影響貸款成數與轉手性——買前先看謄本。 | Y29: housing | AA29: v10.json
A30: OPPORTUNITY_SMALL | B30: OPS_RE8 | C30: REALESTATE | D30: 板橋老公寓一房 | E30: 1150 | F30: 230 | G30: 9.5 | H30: 1.1 | J30: =IF(AND(ISNUMBER(E30),E30>0),(N(G30)-N(H30))*12/E30,"") -> 0.087652174 | W30: 屋齡三十年，但走路到捷運只要五分鐘。 | X30: 地點是不動產最難被時間打敗的部分，屋況可以修，位置不能。 | Y30: housing | AA30: v10.json
A31: OPPORTUNITY_SMALL | B31: OPS_BZ11 | C31: BUSINESS | D31: 嘉義火雞肉飯老店（頂讓） | E31: 220 | I31: 8.5 | J31: =IF(AND(ISNUMBER(E31),E31>0,ISNUMBER(I31)),I31*12/E31,"") -> 0.46363636 | Q31: 是 | W31: 觀光客排隊，在地人外帶，老闆想退休。 | X31: 老店頂讓金裡有多少是「情懷溢價」？回頭客會不會跟著老闆走？ | Y31: business | AA31: v10.json
A32: OPPORTUNITY_SMALL | B32: OPS_BZ12 | C32: BUSINESS | D32: 民雄鵝肉小館（合夥） | E32: 180 | I32: 6.2 | J32: =IF(AND(ISNUMBER(E32),E32>0,ISNUMBER(I32)),I32*12/E32,"") -> 0.41333333 | Q32: 是 | W32: 大學商圈旁，寒暑假人潮少一半。 | X32: 學區生意要用「上課月份」算現金流，別拿旺季直接乘十二。 | Y32: business | AA32: v10.json
A33: OPPORTUNITY_SMALL | B33: OPS_BZ13 | C33: BUSINESS | D33: 中和巷口滷肉飯（加盟） | E33: 130 | I33: 4.6 | J33: =IF(AND(ISNUMBER(E33),E33>0,ISNUMBER(I33)),I33*12/E33,"") -> 0.42461538 | W33: 總部教你滷汁配方，但房租你自己扛。 | X33: 加盟買的是招牌與流程，最大的成本往往在租金與人力。 | Y33: business | AA33: v10.json
A34: OPPORTUNITY_SMALL | B34: OPS_BZ14 | C34: BUSINESS | D34: 永和豆漿早餐店（接手） | E34: 160 | I34: 5.8 | J34: =IF(AND(ISNUMBER(E34),E34>0,ISNUMBER(I34)),I34*12/E34,"") -> 0.435 | Q34: 是 | W34: 凌晨三點開工，中午十二點打烊。 | X34: 高工時生意的「利潤」有一半是你自己的工資——先扣掉再比較。 | Y34: business | AA34: v10.json
A35: OPPORTUNITY_SMALL | B35: OPS_BZ15 | C35: BUSINESS | D35: 泰式小館（雙人創業） | E35: 240 | I35: 8 | J35: =IF(AND(ISNUMBER(E35),E35>0,ISNUMBER(I35)),I35*12/E35,"") -> 0.4 | Q35: 是 | W35: 主廚是曼谷來的，合夥人是你大學同學。 | X35: 餐飲創業先算翻桌率與客單價，再算你們兩人多久不能領薪水。 | Y35: business | AA35: v10.json
A36: OPPORTUNITY_SMALL | B36: OPS_BZ16 | C36: BUSINESS | D36: 健康餐盒中央廚房（小型） | E36: 300 | I36: 10.5 | J36: =IF(AND(ISNUMBER(E36),E36>0,ISNUMBER(I36)),I36*12/E36,"") -> 0.42 | W36: 健身房與上班族訂單穩定，毛利薄。 | X36: 訂閱制生意穩定但毛利薄，量起不來就是白忙。 | Y36: business | AA36: v10.json
A37: OPPORTUNITY_SMALL | B37: OPS_BZ17 | C37: BUSINESS | D37: 手搖珍奶店（商圈店面） | E37: 260 | I37: 9 | J37: =IF(AND(ISNUMBER(E37),E37>0,ISNUMBER(I37)),I37*12/E37,"") -> 0.41538462 | Q37: 是 | W37: 夏天排到轉角，冬天店員比客人多。 | X37: 季節性生意要留過冬現金，旺季賺的錢不是全能花。 | Y37: business | AA37: v10.json
A38: OPPORTUNITY_LARGE | B38: OPL_RE1 | C38: REALESTATE | D38: 台中七期兩房 | E38: 12000 | F38: 2400 | G38: 68 | H38: 8 | J38: =IF(AND(ISNUMBER(E38),E38>0),(N(G38)-N(H38))*12/E38,"") -> 0.06 | N38: 0.022 | O38: 是 | P38: {"RECOVERY": 1.0, "BOOM": 1.35, "RECESSION": 0.85, "DEPRESSION": 0.6} | W38: 面公園，租客是科技業外派主管。 | X38: 大標的每筆現金流大，但要壓上更多自備款。 | Y38: housing、leverage | AA38: base.json
A39: OPPORTUNITY_LARGE | B39: OPL_RE2 | C39: REALESTATE | D39: 台北文山三房 | E39: 18000 | F39: 3600 | G39: 98 | H39: 10 | J39: =IF(AND(ISNUMBER(E39),E39>0),(N(G39)-N(H39))*12/E39,"") -> 0.058666667 | N39: 0.022 | O39: 是 | P39: {"RECOVERY": 1.0, "BOOM": 1.32, "RECESSION": 0.86, "DEPRESSION": 0.62} | W39: 屋主換屋，願意配合貸款流程。 | X39: 利率每升一碼，你的月付息就漲一次——浮動利率是隱形風險。 | Y39: housing、leverage | AA39: base.json
A40: OPPORTUNITY_LARGE | B40: OPL_RE3 | C40: REALESTATE | D40: 新竹科園整層住家 | E40: 15000 | F40: 3000 | G40: 88 | H40: 9 | J40: =IF(AND(ISNUMBER(E40),E40>0),(N(G40)-N(H40))*12/E40,"") -> 0.0632 | N40: 0.023 | O40: 是 | P40: {"RECOVERY": 1.0, "BOOM": 1.4, "RECESSION": 0.8, "DEPRESSION": 0.55} | W40: 竹科上班族排隊等租。 | X40: 單一產業支撐的租金，會跟著那個產業一起循環。 | Y40: housing、leverage | AA40: base.json
A41: OPPORTUNITY_LARGE | B41: OPL_RE4 | C41: REALESTATE | D41: 台南民宿透天 | E41: 9000 | F41: 1800 | G41: 64 | H41: 12 | J41: =IF(AND(ISNUMBER(E41),E41>0),(N(G41)-N(H41))*12/E41,"") -> 0.069333333 | N41: 0.025 | O41: 是 | P41: {"RECOVERY": 1.0, "BOOM": 1.3, "RECESSION": 0.78, "DEPRESSION": 0.5} | W41: 老屋改建，週末訂房滿載。 | X41: 經營型房產報酬高，但你其實買了一份工作。 | Y41: housing、business | AA41: base.json
A42: OPPORTUNITY_LARGE | B42: OPL_RE5 | C42: REALESTATE | D42: 商辦分層出租 | E42: 22000 | F42: 4400 | G42: 132 | H42: 14 | J42: =IF(AND(ISNUMBER(E42),E42>0),(N(G42)-N(H42))*12/E42,"") -> 0.064363636 | N42: 0.024 | O42: 是 | P42: {"RECOVERY": 1.0, "BOOM": 1.45, "RECESSION": 0.72, "DEPRESSION": 0.45} | W42: 整層八個隔間，六家新創進駐。 | X42: 商用不動產的租金隨景氣擺動比住宅劇烈。 | Y42: commercial、leverage | AA42: base.json
A43: OPPORTUNITY_LARGE | B43: OPL_RE6 | C43: REALESTATE | D43: 社區車位八席 | E43: 4800 | F43: 960 | G43: 34 | H43: 2 | J43: =IF(AND(ISNUMBER(E43),E43>0),(N(G43)-N(H43))*12/E43,"") -> 0.08 | N43: 0.026 | O43: 是 | P43: {"RECOVERY": 1.0, "BOOM": 1.25, "RECESSION": 0.9, "DEPRESSION": 0.7} | W43: 沒有房客糾紛，也沒有漏水。 | X43: 管理成本低的資產，現金流最乾淨。 | Y43: housing | AA43: base.json
A44: OPPORTUNITY_LARGE | B44: OPL_BZ1 | C44: BUSINESS | D44: 連鎖早餐店三家 | E44: 3200 | I44: 88 | J44: =IF(AND(ISNUMBER(E44),E44>0,ISNUMBER(I44)),I44*12/E44,"") -> 0.33 | Q44: 否 | W44: 原老闆要退休，員工全數留任。 | X44: 買下有店長的生意，你買的是系統不是工作。 | Y44: business | AA44: base.json
A45: OPPORTUNITY_LARGE | B45: OPL_BZ2 | C45: BUSINESS | D45: 小型物流車隊 | E45: 5000 | I45: 128 | J45: =IF(AND(ISNUMBER(E45),E45>0,ISNUMBER(I45)),I45*12/E45,"") -> 0.3072 | Q45: 是 | W45: 綁三家電商的最後一哩配送。 | X45: 客戶集中度是風險：三家跑掉一家，利潤少三分之一。 | Y45: business | AA45: base.json
A46: OPPORTUNITY_LARGE | B46: OPL_SU1 | C46: STARTUP | D46: AI 客服新創 A 輪 | K46: 1500 | L46: 0.08 | M46: 18750 | W46: 創辦人是你以前的同事。 | X46: 新創股權買的是未來，它現在一毛現金流都不會給你。 | Y46: startup | Z46: M3 | AA46: base.json
A47: OPPORTUNITY_LARGE | B47: OPL_SU2 | C47: STARTUP | D47: 生技檢測新創 B 輪 | K47: 2500 | L47: 0.1 | M47: 25000 | W47: 剛拿到醫材許可證。 | X47: 下一輪你若不跟投，股份會被稀釋——這是股權投資的必修課。 | Y47: startup | Z47: M3 | AA47: base.json
A48: OPPORTUNITY_LARGE | B48: OPP_OFFSHORE_VIP_FUND | C48: BUSINESS | D48: 海外頂級機構專屬配息信託 | E48: 800 | F48: 800 | I48: 36 | J48: =IF(AND(ISNUMBER(E48),E48>0,ISNUMBER(I48)),I48*12/E48,"") -> 0.54 | R48: 是 | S48: 4 | U48: 海外信託 | V48: INNER | W48: 理專小聲透露：這是資產千萬以上的 VIP 才能投的海外配息基金，年化 54%、零風險。 | X48: 不在金融監管名冊內的境外商品，一旦出事跨國追償往往化為烏有（歷史原型：澳豐金融案）。 | AA48: base.json
A49: OPPORTUNITY_LARGE | B49: OPL_RE7 | C49: REALESTATE | D49: 逢甲學生宅整棟 | E49: 16000 | F49: 3200 | G49: 92 | H49: 11 | J49: =IF(AND(ISNUMBER(E49),E49>0),(N(G49)-N(H49))*12/E49,"") -> 0.06075 | W49: 十二間套房，寒暑假空一半。 | X49: 整棟收租看的是「實際入住率」，不是滿租試算表。 | Y49: housing、leverage | AA49: v10.json
A50: OPPORTUNITY_LARGE | B50: OPL_RE8 | C50: REALESTATE | D50: 宜蘭田中央民宿 | E50: 8500 | F50: 1700 | G50: 58 | H50: 7 | J50: =IF(AND(ISNUMBER(E50),E50>0),(N(G50)-N(H50))*12/E50,"") -> 0.072 | W50: 假日一房難求，平日一片安靜。 | X50: 旅宿業是「單價 × 住房率」的生意，兩個數字都會被景氣打。 | Y50: housing | AA50: v10.json
A51: OPPORTUNITY_LARGE | B51: OPL_BZ3 | C51: BUSINESS | D51: 連鎖洗衣加盟五店 | E51: 4200 | I51: 112 | J51: =IF(AND(ISNUMBER(E51),E51>0,ISNUMBER(I51)),I51*12/E51,"") -> 0.32 | W51: 總部包裝潢與設備，你出資金與人。 | X51: 加盟金與權利金是固定成本，展店前先算「幾家才會賺」。 | Y51: business | AA51: v10.json
A52: OPPORTUNITY_LARGE | B52: OPL_BZ4 | C52: BUSINESS | D52: 老街文青咖啡館（整棟改裝） | E52: 2600 | I52: 58 | J52: =IF(AND(ISNUMBER(E52),E52>0,ISNUMBER(I52)),I52*12/E52,"") -> 0.26769231 | Q52: 是 | W52: 打卡的人很多，坐下來點單的少一點。 | X52: 「氛圍財」景氣好時最旺、反轉時最先被砍——這是可支配支出的第一線。 | Y52: business | AA52: v10.json
A53: OPPORTUNITY_LARGE | B53: OPL_BZ5 | C53: BUSINESS | D53: 國際連鎖咖啡（加盟主力店） | E53: 5200 | I53: 145 | J53: =IF(AND(ISNUMBER(E53),E53>0,ISNUMBER(I53)),I53*12/E53,"") -> 0.33461538 | W53: 品牌自帶客流，權利金也自帶抽成。 | X53: 大品牌加盟：營收穩定換抽成——算的是「穩定折價」值不值。 | Y53: business | AA53: v10.json
A54: OPPORTUNITY_LARGE | B54: OPL_BZ6 | C54: BUSINESS | D54: 連鎖便利商店（雙店加盟） | E54: 3600 | I54: 96 | J54: =IF(AND(ISNUMBER(E54),E54>0,ISNUMBER(I54)),I54*12/E54,"") -> 0.32 | W54: 24 小時亮著燈，大夜班永遠在徵人。 | X54: 多店加盟賺的是規模，但兩家店的人事問題不止兩倍。 | Y54: business | AA54: v10.json
A55: OPPORTUNITY_LARGE | B55: OPM_RE1 | C55: REALESTATE | D55: 三重五股透天一樓（三戶合租） | E55: 3000 | F55: 600 | G55: 22 | H55: 4 | J55: =IF(AND(ISNUMBER(E55),E55>0),(N(G55)-N(H55))*12/E55,"") -> 0.072 | N55: 0.022 | O55: 是 | P55: {"RECOVERY": 1, "BOOM": 1.3, "RECESSION": 0.86, "DEPRESSION": 0.62} | T55: 是 | W55: 屋主急脫手，開價比行情低一成，但要現金到位快。 | X55: 頭款兩成，剩下八成是銀行的。合資的話你出的是頭款的一部分，槓桿沒有變小。 | Y55: housing、leverage、jv | AA55: v10.json
A56: OPPORTUNITY_LARGE | B56: OPM_RE2 | C56: REALESTATE | D56: 中壢工業區小廠辦 | E56: 4000 | F56: 800 | G56: 29 | H56: 6 | J56: =IF(AND(ISNUMBER(E56),E56>0),(N(G56)-N(H56))*12/E56,"") -> 0.069 | N56: 0.022 | O56: 是 | P56: {"RECOVERY": 1, "BOOM": 1.26, "RECESSION": 0.88, "DEPRESSION": 0.66} | T56: 是 | W56: 租給模具廠，租約三年一簽。 | X56: 單一租客的物件，空租一次就吃掉整年報酬——分散不只講在股票上。 | Y56: housing、leverage、jv | AA56: v10.json
A57: OPPORTUNITY_LARGE | B57: OPM_RE3 | C57: REALESTATE | D57: 台南永康學區整層四套 | E57: 5000 | F57: 1000 | G57: 37 | H57: 9 | J57: =IF(AND(ISNUMBER(E57),E57>0),(N(G57)-N(H57))*12/E57,"") -> 0.0672 | N57: 0.022 | O57: 是 | P57: {"RECOVERY": 1, "BOOM": 1.3, "RECESSION": 0.86, "DEPRESSION": 0.62} | T57: 是 | W57: 四間套房分租，管理費另計。 | X57: 四個租客比一個穩，但也代表四倍的維修與催租。 | Y57: housing、leverage、jv | AA57: v10.json
A58: OPPORTUNITY_LARGE | B58: OPM_RE4 | C58: REALESTATE | D58: 高雄亞灣區兩房（法拍取得） | E58: 6000 | F58: 1200 | G58: 45 | H58: 10 | J58: =IF(AND(ISNUMBER(E58),E58>0),(N(G58)-N(H58))*12/E58,"") -> 0.07 | N58: 0.024 | O58: 是 | P58: {"RECOVERY": 1, "BOOM": 1.26, "RECESSION": 0.88, "DEPRESSION": 0.66} | T58: 是 | W58: 法拍屋，點交順利但要一次付清尾款。 | X58: 便宜有便宜的理由：法拍的折價，買的是你自己承擔的麻煩。 | Y58: housing、leverage、jv | AA58: v10.json
A59: OPPORTUNITY_LARGE | B59: OPM_BZ1 | C59: BUSINESS | D59: 社區型健身工作室（頂讓） | E59: 700 | I59: 22 | J59: =IF(AND(ISNUMBER(E59),E59>0,ISNUMBER(I59)),I59*12/E59,"") -> 0.37714286 | Q59: 是 | T59: 是 | W59: 現有會員 180 人，教練願意留任。 | X59: 會員制的生意，現金流看起來很穩——直到續約季。 | Y59: business、jv | AA59: v10.json
A60: OPPORTUNITY_LARGE | B60: OPM_BZ2 | C60: BUSINESS | D60: 連鎖手搖飲兩店（雙店包） | E60: 900 | I60: 27 | J60: =IF(AND(ISNUMBER(E60),E60>0,ISNUMBER(I60)),I60*12/E60,"") -> 0.36 | Q60: 否 | T60: 是 | W60: 兩間店綁一起賣，單買不拆。 | X60: 綁售的兩店裡通常有一間是拖油瓶。買之前要分開看兩本帳。 | Y60: business、jv | AA60: v10.json
A61: OPPORTUNITY_LARGE | B61: OPM_BZ3 | C61: BUSINESS | D61: 校園周邊自助洗衣三店 | E61: 1100 | I61: 32 | J61: =IF(AND(ISNUMBER(E61),E61>0,ISNUMBER(I61)),I61*12/E61,"") -> 0.34909091 | Q61: 否 | T61: 是 | W61: 三間店同一個商圈，共用一台補鈔車。 | X61: 同一個商圈的三間店不是分散，是集中——商圈衰退時一起衰退。 | Y61: business、jv | AA61: v10.json
A62: OPPORTUNITY_LARGE | B62: OPM_BZ4 | C62: BUSINESS | D62: 區域型烘焙中央廚房 | E62: 1200 | I62: 34 | J62: =IF(AND(ISNUMBER(E62),E62>0,ISNUMBER(I62)),I62*12/E62,"") -> 0.34 | Q62: 是 | T62: 是 | W62: 供應八間早餐店，客戶集中但穩定。 | X62: B2B 的生意毛利低但量大；最大的風險是最大的那個客戶。 | Y62: business、jv | AA62: v10.json
A63: OPPORTUNITY_SPECIAL | B63: SP01 | C63: BUSINESS | D63: 同學的連鎖藥妝店，缺一個股東 | E63: 6000 | I63: 204 | J63: =IF(AND(ISNUMBER(E63),E63>0,ISNUMBER(I63)),I63*12/E63,"") -> 0.408 | Q63: 是 | W63: EMBA 同組報告的那個人，開口第一句是「先問你要不要」。 | X63: 最好的案子從來不會出現在公開市場——但這不代表它們沒有風險。 | AA63: special.json
A64: OPPORTUNITY_SPECIAL | B64: SP02 | C64: REALESTATE | D64: 校友讓出的市中心整層商辦 | E64: 24000 | F64: 4800 | G64: 170 | H64: 16 | J64: =IF(AND(ISNUMBER(E64),E64>0),(N(G64)-N(H64))*12/E64,"") -> 0.077 | W64: 他要移民，開的價比市場低一成，條件是三週內完成。 | X64: 人脈換到的是「先看到」和「談得動」，不是「一定賺」——你還是要自己算。 | AA64: special.json
A65: OPPORTUNITY_SPECIAL | B65: SP03 | C65: STARTUP | D65: 指導教授的實驗室要衍生新創 | K65: 2000 | L65: 0.12 | M65: 16000 | W65: 技術還在論文階段，但團隊你認識三個。 | X65: 看得懂技術不等於看得懂生意；認識創辦人也不等於降低風險。沒有月現金流，全押在退出價差上。 | AA65: special.json
A66: OPPORTUNITY_SPECIAL | B66: SP04 | C66: BUSINESS | D66: 學長的區域物流站要頂讓 | E66: 7500 | I66: 264 | J66: =IF(AND(ISNUMBER(E66),E66>0,ISNUMBER(I66)),I66*12/E66,"") -> 0.4224 | Q66: 是 | W66: 他升上去了，站點要交給信得過的人。 | X66: 「信得過的人」是一種折價，但接手後每天要面對的是同一批車和同一批司機。 | AA66: special.json
A67: OPPORTUNITY_SPECIAL | B67: SP05 | C67: REALESTATE | D67: 同學家族的老市場店面（三代持有） | E67: 20000 | F67: 4000 | G67: 146 | H67: 12 | J67: =IF(AND(ISNUMBER(E67),E67>0),(N(G67)-N(H67))*12/E67,"") -> 0.0804 | W67: 從不掛牌，這次是因為要分家。 | X67: 稀缺的東西通常也難脫手——買之前先想清楚你打算怎麼賣掉它。 | AA67: special.json
A68: OPPORTUNITY_SPECIAL | B68: SP06 | C68: BUSINESS | D68: 同學新開的寵物旅館，找人一起出 | E68: 800 | I68: 27 | J68: =IF(AND(ISNUMBER(E68),E68>0,ISNUMBER(I68)),I68*12/E68,"") -> 0.405 | Q68: 是 | T68: 是 | W68: EMBA 分組報告的組員，週末帶你去看場地。 | X68: 入場金額小不代表風險小——人脈帶來的案子，最貴的成本是拉不下臉拒絕。 | AA68: special.json
A69: OPPORTUNITY_SPECIAL | B69: SP07 | C69: BUSINESS | D69: 教授實驗室的檢測服務要對外接單 | E69: 1200 | I69: 39 | J69: =IF(AND(ISNUMBER(E69),E69>0,ISNUMBER(I69)),I69*12/E69,"") -> 0.39 | Q69: 否 | T69: 是 | W69: 「先做小的試試看」，教授這樣說。 | X69: 小額入場的好處是可以先試水溫。真正的門票是那通電話，不是那筆錢。 | AA69: special.json
A70: OPPORTUNITY_SPECIAL | B70: SP08 | C70: BUSINESS | D70: 學長的連鎖洗車據點，缺一個小股東 | E70: 1600 | I70: 55 | J70: =IF(AND(ISNUMBER(E70),E70>0,ISNUMBER(I70)),I70*12/E70,"") -> 0.4125 | Q70: 是 | T70: 是 | W70: 他只缺一個名額，開口就說金額不用大。 | X70: 小股東拿得到分潤，但拿不到決定權。入股前先問清楚誰說了算。 | AA70: special.json

Sheet 人生事件卡
A1: FinFlow 內容盤點｜人生事件卡
A2: LIFE_EVENT（含二選一 CHOICE、自我投資 SELF_INVEST、獨立董事邀請 SPECIAL）＋ 職業事件 ＋ 夢想圈事件 OUTER_LIFE。技能情境卡另列「學習-情境卡」。金額單位＝千元。
A4: 牌堆 | B4: id | C4: 類型 | D4: 子類 | E4: 標題 | F4: 副標 | G4: 情境 | H4: 教育註記 | I4: 效果 | J4: 選項（二選一） | K4: 品格分歧 | L4: 費用 | M4: 幸福感 | N4: 可選 | O4: 開的決策 | P4: 一生一次 | Q4: 需要小孩 | R4: 需任一技能 | S4: 不得已有技能 | T4: 需正在學習 | U4: 限定職業 | V4: 分組 | W4: 階段 | X4: 標籤 | Y4: 模組 | Z4: 來源檔
A5: LIFE_EVENT | B5: LE01 | C5: LIFE_EVENT | E5: 家裡多了一個人 | G5: 半夜的哭聲從此變成背景音。 | H5: 每個孩子都是一筆長期的月支出，要提早進預算。 | I5: 生小孩 | X5: family | Z5: base.json
A6: LIFE_EVENT | B6: LE02 | C6: LIFE_EVENT | E6: 年度調薪 | G6: 主管說你今年表現很好。 | H6: 加薪讓你更快存到本金，但它不會自己變成被動收入。 | I6: 薪水× ×1.08（年度調薪） | X6: career | Z6: base.json
A7: LIFE_EVENT | B7: LE04 | C7: LIFE_EVENT | E7: 急性盲腸炎 | G7: 半夜掛急診。 | H7: 醫療支出是最典型的「必須有現金」情境。 | I7: 現金 -30 對象:自己（醫療自付） | X7: health | Z7: base.json
A8: LIFE_EVENT | B8: LE05 | C8: LIFE_EVENT | E8: 長輩留下的一筆錢 | G8: 信封上寫著你的名字。 | H8: 一次性收入是存量，把它換成會生錢的資產才會變流量。 | I8: 現金 +260 對象:自己（繼承） | X8: windfall | Z8: base.json
A9: LIFE_EVENT | B9: LE06 | C9: LIFE_EVENT | E9: 二寶報到 | G9: 這次比較從容一點。 | H9: 養育支出是等比級數，不是加法。 | I9: 生小孩 | X9: family | Z9: base.json
A10: LIFE_EVENT | B10: LE07 | C10: LIFE_EVENT | E10: 被挖角跳槽 | G10: 對方開的價碼你想了三天。 | H10: 換工作是提高主動收入最快的方式之一。 | I10: 薪水× ×1.15（跳槽加薪）；現金 -12 對象:自己（空窗期支出） | X10: career | Z10: base.json
A11: LIFE_EVENT | B11: LE08 | C11: LIFE_EVENT | E11: 親戚的婚宴週 | G11: 一週三場，都是不能不去的。 | H11: 可預測的人情支出應該編進年度預算。 | I11: 現金 -18 對象:自己（禮金） | X11: social | Z11: base.json
A12: LIFE_EVENT | B12: LE10 | C12: LIFE_EVENT | E12: 三寶出生 | G12: 家裡真的滿了。 | H12: 家庭規模是你自由門檻的乘數。 | I12: 生小孩 | X12: family | Z12: base.json
A13: LIFE_EVENT | B13: SI_MBA | C13: SELF_INVEST | E13: 在職進修念個 MBA | G13: 週末與夜晚全給了課本，兩年後履歷不一樣了。 | H13: 對自己的投資，長期報酬率常常最高。 | J13: 1. 投資自己｜投入 60 薪資 ×1.28｜費用 60｜效果：現金 -60 對象:自己（在職進修念個 MBA 投入）；薪水× ×1.28 對象:自己（在職進修念個 MBA） 2. 暫時不｜把錢與時間留著 | P13: 是 | Z13: base.json
A14: LIFE_EVENT | B14: SI_CERT | C14: SELF_INVEST | E14: 考取國際專業證照 | G14: 考場外的你，比進場前更值錢。 | H14: 證照是把能力標準化、讓市場看得見。 | J14: 1. 投資自己｜投入 28 薪資 ×1.18｜費用 28｜效果：現金 -28 對象:自己（考取國際專業證照 投入）；薪水× ×1.18 對象:自己（考取國際專業證照） 2. 暫時不｜把錢與時間留著 | P14: 是 | Z14: base.json
A15: LIFE_EVENT | B15: SI_PIVOT | C15: SELF_INVEST | E15: 轉職到成長型產業 | G15: 空窗與從頭學起的陣痛，換來更高的天花板。 | H15: 選對產業，努力的邊際報酬會完全不同。 | J15: 1. 投資自己｜投入 20 薪資 ×1.22｜費用 20｜效果：現金 -20 對象:自己（轉職到成長型產業 投入）；薪水× ×1.22 對象:自己（轉職到成長型產業） 2. 暫時不｜把錢與時間留著 | P15: 是 | Z15: base.json
A16: LIFE_EVENT | B16: SI_SKILL | C16: SELF_INVEST | E16: 學會第二專長（數位技能） | G16: 下班後的線上課，補上了缺的那塊拼圖。 | H16: 一技之長，是通膨時代最保值的資產。 | J16: 1. 投資自己｜投入 22 薪資 ×1.16｜費用 22｜效果：現金 -22 對象:自己（學會第二專長（數位技能） 投入）；薪水× ×1.16 對象:自己（學會第二專長（數位技能）） 2. 暫時不｜把錢與時間留著 | P16: 是 | Z16: base.json
A17: LIFE_EVENT | B17: SI_NEGO | C17: SELF_INVEST | E17: 上完溝通課，成功談加薪 | G17: 你準備了數據、也準備了勇氣。 | H17: 你的薪水，有時只差一次好好開口。 | J17: 1. 投資自己｜投入 8 薪資 ×1.12｜費用 8｜效果：現金 -8 對象:自己（上完溝通課，成功談加薪 投入）；薪水× ×1.12 對象:自己（上完溝通課，成功談加薪） 2. 暫時不｜把錢與時間留著 | P17: 是 | Z17: base.json
A18: LIFE_EVENT | B18: SI_LANG | C18: SELF_INVEST | E18: 進修外語，爭取外派加給 | G18: 多會一種語言，就多一種人生選項。 | H18: 語言打開的是機會，不只是履歷。 | J18: 1. 投資自己｜投入 30 薪資 ×1.25｜費用 30｜效果：現金 -30 對象:自己（進修外語，爭取外派加給 投入）；薪水× ×1.25 對象:自己（進修外語，爭取外派加給） 2. 暫時不｜把錢與時間留著 | P18: 是 | Z18: base.json
A19: LIFE_EVENT | B19: SI_SIDE | C19: SELF_INVEST | E19: 副業起步：週末工作坊 | G19: 把興趣變成收入，週末不再只是休息。 | H19: 第二收入來源，是抗風險的底氣。 | J19: 1. 投資自己｜投入 18 薪資 ×1.15｜費用 18｜效果：現金 -18 對象:自己（副業起步：週末工作坊 投入）；薪水× ×1.15 對象:自己（副業起步：週末工作坊） 2. 暫時不｜把錢與時間留著 | P19: 是 | Z19: base.json
A20: LIFE_EVENT | B20: SI_QUIT | C20: SELF_INVEST | E20: 戒除昂貴習慣，重整生活 | G20: 算了一次年度花費，你嚇了一跳。 | H20: 省下的每一塊，都是自由的一小步。 | J20: 1. 投資自己｜投入 5 每月支出 -5｜費用 5｜效果：現金 -5 對象:自己（戒除昂貴習慣，重整生活 投入）；每月支出（限時） -5 對象:自己（戒除昂貴習慣，重整生活（每月）） 2. 暫時不｜把錢與時間留著 | P20: 是 | Z20: base.json
A21: LIFE_EVENT | B21: SI_MOVE | C21: SELF_INVEST | E21: 搬到房租更合理的地方 | G21: 通勤多十分鐘，錢包鬆了一大截。 | H21: 居住成本，是多數人最大的固定支出。 | J21: 1. 投資自己｜投入 10 每月支出 -6｜費用 10｜效果：現金 -10 對象:自己（搬到房租更合理的地方 投入）；每月支出（限時） -6 對象:自己（搬到房租更合理的地方（每月）） 2. 暫時不｜把錢與時間留著 | P21: 是 | Z21: base.json
A22: LIFE_EVENT | B22: SI_AUTO | C22: SELF_INVEST | E22: 建立自動化理財系統 | G22: 設定好自動轉帳與記帳，錢就乖了。 | H22: 好的系統，讓省錢不必靠意志力。 | J22: 1. 投資自己｜投入 6 每月支出 -3｜費用 6｜效果：現金 -6 對象:自己（建立自動化理財系統 投入）；每月支出（限時） -3 對象:自己（建立自動化理財系統（每月）） 2. 暫時不｜把錢與時間留著 | P22: 是 | Z22: base.json
A23: LIFE_EVENT | B23: SI_HEALTH | C23: SELF_INVEST | E23: 認真投資健康，減少醫療支出 | G23: 開始運動與定期檢查後，藥費省下來了。 | H23: 健康是負債表上看不到、卻最貴的資產。 | J23: 1. 投資自己｜投入 20 每月支出 -4｜費用 20｜效果：現金 -20 對象:自己（認真投資健康，減少醫療支出 投入）；每月支出（限時） -4 對象:自己（認真投資健康，減少醫療支出（每月）） 2. 暫時不｜把錢與時間留著 | P23: 是 | Z23: base.json
A24: LIFE_EVENT | B24: SI_DEBT | C24: SELF_INVEST | E24: 把高利卡債整合成低利貸 | G24: 一通電話、一張表，利息砍了一半。 | H24: 先解決最貴的債，比多賺更有效。 | J24: 1. 投資自己｜投入 4 每月支出 -5｜費用 4｜效果：現金 -4 對象:自己（把高利卡債整合成低利貸 投入）；每月支出（限時） -5 對象:自己（把高利卡債整合成低利貸（每月）） 2. 暫時不｜把錢與時間留著 | P24: 是 | Z24: base.json
A25: LIFE_EVENT | B25: LE11 | C25: CHOICE | E25: 父母醫療陪同請假 | G25: 爸媽要回診，時間卡在上班日。 | H25: 陪伴的價值不在報酬率，但會回到你們的關係裡。 | J25: 1. 請假陪同就醫｜花 9、停 1 回合；孝親好感 +1、幸福感上升｜費用 9｜效果：現金 -9 對象:自己（陪同請假）；停走 1 輪；品格 孝親+1 2. 忙不過來，這次沒陪｜省下時間與錢，但父母有點失落（孝親好感 −1）｜效果：品格 孝親-1 | X25: insurable、medical | Y25: M6 | Z25: base.json
A26: LIFE_EVENT | B26: LE09 | C26: CHOICE | E26: 照顧生病的家人 | G26: 家人住院了，需要有人在身邊。 | H26: 時間與金錢常要二選一，沒有標準答案。 | J26: 1. 親自照顧｜花 15、停 1 回合；孝親好感 +1、幸福感上升｜費用 15｜效果：現金 -15 對象:自己（照護支出）；停走 1 輪；品格 孝親+1 2. 花錢請看護代勞｜花 30、多花錢換時間，關係持平｜費用 30｜效果：現金 -30 對象:自己（看護費） | X26: insurable、medical | Y26: M6 | Z26: base.json
A27: LIFE_EVENT | B27: LE12 | C27: LIFE_EVENT | E27: 開車擦撞，對方要求賠償 | G27: 路口一個閃神，保險桿凹了一角。 | H27: 車險與緊急預備金，就是為這種「一定會發生的意外」準備的。 | I27: 現金 -28 對象:自己（修車與和解金） | X27: insurable、accident | Z27: base.json
A28: LIFE_EVENT | B28: LE13 | C28: LIFE_EVENT | E28: 騎車犁田，手臂擦傷 | G28: 雨天路滑，人和車一起滑出去。 | H28: 機車族的醫療與修車支出，發生率比想像高得多。 | I28: 現金 -18 對象:自己（醫療自付與修車） | X28: insurable、medical | Z28: base.json
A29: LIFE_EVENT | B29: LE14 | C29: LIFE_EVENT | E29: 寵物生病掛急診 | G29: 半夜牠一直吐，你抱著牠衝獸醫院。 | H29: 獸醫沒有健保——養寵物前，醫療預備金要先想好。 | I29: 現金 -16 對象:自己（獸醫急診費） | X29: family、pet | Z29: base.json
A30: LIFE_EVENT | B30: LE15 | C30: CHOICE | E30: 交往對象出現了 | G30: 聊得來的人不常有，這次好像是真的。 | H30: 感情是資產負債表外最重要的一項，但約會預算要入表。 | J30: 1. 認真交往｜一次 10（治裝與約會）＋每月 4 約會開銷｜費用 10｜效果：現金 -10 對象:自己（治裝與約會）；每月支出（限時） +4（每月約會開銷） 2. 先專注拚事業｜把時間與錢留給自己 | P30: 是 | X30: family | Z30: base.json
A31: LIFE_EVENT | B31: EVT_GRAD_TRIP_PARIS_BALI | C31: CHOICE | E31: 一生一次的畢業旅行 | G31: 開拓視野不一定要背負沉重債務；用適合自己口袋的方式創造回憶，才不會讓未來的自己替現在的浪漫買單。 | H31: 體驗無價，但打腫臉充胖子的分期付款會讓未來的現金流嚴重窒息。 | J31: 1. 🚲 去新北淡水八里（小資浪漫）｜支出 6、幸福感 +2，情緒修養 +1｜費用 6｜效果：現金 -6；幸福感 +2；品格 情緒+1 2. ✈️ 飛法國巴黎（奢華遠征）｜支出 80、幸福感 +4，獲國際視野｜費用 80｜效果：現金 -80；幸福感 +4 | V31: 青春與成長 | W31: INNER | Z31: base.json
A32: LIFE_EVENT | B32: CHOICE_MOTO_MONKEY | C32: CHOICE | E32: 山道猴子的重機誘惑 | G32: 車行老闆熱情招攬：『少年欸，零元交車、免頭期，分期 84 期輕鬆繳，再送全車彩貼！』 | H32: 買車是一時的快感，養車是每月雷打不動的現金流失血（油錢、保養、保險、折舊）。 | J32: 1. 🛵 騎家裡買菜車｜理智清醒，支出 0，謹慎修養 +1｜效果：品格 守法謹慎+1 2. 🏍 簽下去零元交車｜每月固定支出 +4.5 持續 2 年，幸福感 +3｜效果：每月支出（限時） +4.5 持續 24 輪；幸福感 +3 | V32: 生活誘惑 | W32: INNER | Z32: base.json
A33: LIFE_EVENT | B33: CHOICE_SUGAR_AUNTIE | C33: CHOICE | E33: 神秘名媛的捷徑私訊 | G33: 私訊說只要「借」提款卡和帳戶給她走帳幾天，就先給十萬謝禮，還要介紹貴人。 | H33: 借出銀行帳戶在法律上視為詐欺幫助犯，將面臨帳戶凍結與全額求償。 | J33: 1. 💡 果斷封鎖檢舉｜守住底線，謹慎修養 +1｜效果：品格 守法謹慎+1 2. ⚠️ 冒險走捷徑赴約｜現拿 100，但 2 輪後帳戶遭凍結：追償 130、停走 1 輪、謹慎 −2｜效果：現金 +100；品格 守法謹慎-2；延後引爆 2 輪後：現金 -130；停走 1 輪；幸福感 -2（人頭帳戶遭凍結，警示帳戶與被害人求償） | V33: 灰色誘惑 | W33: INNER | Z33: base.json
A34: LIFE_EVENT | B34: CHOICE_DAY_TRADING_GOD | C34: CHOICE | E34: 少年股神當沖衝鋒 | G34: 論壇每天都在曬當沖無本翻倍對帳單，同學慫恿：『不開槓桿怎麼翻身？一萬塊也能玩！』 | H34: 過度自信與頻繁當沖是散戶資本蒸發的主因，唯有紀律與複利能穿越週期。 | J34: 1. 📈 堅持定期定額指數 ETF｜穩健複利，守法謹慎 +1｜效果：品格 守法謹慎+1 2. 🎰 賭一把全倉當沖｜違約交割慘賠 150，幸福感 −2｜費用 150｜效果：現金 -150；幸福感 -2 | V34: 投資考驗 | W34: INNER | Z34: base.json
A35: LIFE_EVENT | B35: CHOICE_CONTRACT_LOOPHOLE | C35: CHOICE | E35: 合約漏洞的道德抉擇 | G35: 商譽是累積最慢、摧毀最快的無形資產；在沒人看見時做出的決定定義了你的品德。 | H35: 誠信經商在短期看似放棄便宜，長期卻能累積最深厚的人脈信任紅利。 | J35: 1. 🤝 主動告知並重新修正合約｜守法謹慎 +1，幸福感 +1｜效果：品格 守法謹慎+1；幸福感 +1 2. 💸 裝作不知情鑽漏洞解約｜現賺 100，但謹慎 −2｜效果：現金 +100；品格 守法謹慎-2 | V35: 商業誠信 | W35: INNER | Z35: base.json
A36: LIFE_EVENT | B36: DAILY_CRAM_SCHOOL_BILL | C36: CHOICE | E36: 孩子的補習班繳費單 | G36: 繳費單上的數字，是每個月默默省下來的餐費與加班換來的。 | H36: 教育是報酬率最高的長期投資，但它是真金白銀的固定支出——要排進預算，不是靠餘錢。 | J36: 1. 📖 咬牙繳，陪孩子把書讀好｜支出 15；教養 +1、幸福感 +1｜費用 15｜效果：現金 -15；品格 教養+1；幸福感 +1 2. 🏠 退掉補習，自己每晚盯功課｜省下 15，但下班後的時間都沒了：幸福感 −1｜效果：幸福感 -1 | Q36: 是 | V36: 家庭反思 | W36: INNER | Z36: base.json
A37: LIFE_EVENT | B37: DAILY_PARENT_NIGHT_CALL | C37: CHOICE | E37: 長輩深夜的問候電話 | G37: 陪伴不是剩餘時間的施捨，而是情感帳戶的日常存款。 | H37: 再成功的事業也無法彌補家庭關係的疏離，溫暖傾聽能滋養一生的內心力量。 | J37: 1. ❤️ 放慢呼吸耐心聆聽 20 分鐘｜孝親好感 +1，幸福感 +1｜效果：品格 孝親+1；幸福感 +1 2. 💨 抱怨疲累匆匆掛斷｜孝親好感 −1｜效果：品格 孝親-1 | V37: 孝親家庭 | W37: INNER | Z37: base.json
A38: LIFE_EVENT | B38: LE_INDEPENDENT_DIRECTOR | C38: SPECIAL | E38: 知名企業獨立董事邀請 | F38: 獵頭推薦高階董監席次，享每月車馬費與社會聲望，但須承擔重大連帶法定義務。 | G38: 董事會審計委員會的席次虛位以待，車馬費優厚，但也是地雷公司的祭品首選。 | H38: 獨立董事不只是車馬費；若缺乏審計查核能力，假帳弊案爆發時要面對連帶民事賠償（現實中動輒上億）。 | O38: APPOINT_DIRECTOR | R38: SKL_BOOK、SKL_CPA_AUDIT、SKL_LAW、SKL_GOV_LEGAL | V38: 獨立董監 | Z38: base.json
A39: LIFE_EVENT | B39: SKE_OT | C39: LIFE_EVENT | E39: 公司臨時接了急單，連兩週加班 | G39: 下班走出大樓時，補習班已經拉下鐵門。 | H39: 學習最貴的成本從來不是學費，是你被別的事情吃掉的時間。 | I39: 學習延後 1 輪（加班中斷進度） | T39: 是 | Y39: M8 | Z39: skill.json
A40: LIFE_EVENT | B40: SKE_CAREGIVE | C40: LIFE_EVENT | E40: 家裡有人住院，你請假輪班照顧 | G40: 課本躺在醫院陪病床邊，一頁都沒翻。 | H40: 人生不會等你把課上完才發生。計畫要留餘裕，餘裕就是你的護城河。 | I40: 學習延後 1 輪（照顧家人中斷進度）；現金 -8（看護與交通） | T40: 是 | Y40: M8 | Z40: skill.json
A41: LIFE_EVENT | B41: SKE_INTRAIN | C41: LIFE_EVENT | E41: 公司開了一堂內訓，人資問你要不要去 | G41: 名額有限，週六整天，不強制。 | H41: 別人給的機會也是機會——但通常只留給願意犧牲週六的人。 | I41: 現金 -3（教材與交通）；送技能 SKL_BOOK（公司內訓） | S41: SKL_BOOK | Y41: M8 | Z41: skill.json
A42: PROFESSION_EVENT | B42: PE_CPA_EXAM | C42: PROFESSION_EVENT | E42: 會計師考試放榜季 | G42: 學長姐都說：熬過去，名字就不一樣了。 | H42: 證照是用今天的現金與時間，買未來每個月的加薪——這就是投資自己。 | J42: 1. 全力衝刺應考｜支出 80，停走 1 回合，考取後薪資 +40%｜效果：現金 -80 對象:自己（補習與考試費）；停走 1 輪；薪水× ×1.4（考取會計師） 2. 今年先不考｜保留現金與時間 | P42: 是 | U42: PRO_AUDITOR | X42: career | Z42: base.json
A43: PROFESSION_EVENT | B43: PE_SEMI_BONUS | C43: PROFESSION_EVENT | E43: 分紅入帳日 | G43: 全公司的走廊今天都在笑。 | H43: 一次性獎金是存量不是流量——它不會讓你自由，除非你把它換成會生現金流的資產。 | I43: 現金 +220 對象:自己（年度分紅） | U43: PRO_SEMI | X43: career、windfall | Z43: base.json
A44: OUTER_LIFE | B44: OL_D01 | C44: LIFE_EVENT | E44: 熱水器壽終正寢 | G44: 洗到一半變冷水，人生突然很清醒。 | H44: 自由圈沒有薪水，柴米油鹽照樣找上門——生活準備金不能圓夢圓掉。 | I44: 現金 -35 對象:自己（換新熱水器） | Z44: outer.json
A45: OUTER_LIFE | B45: OL_D02 | C45: LIFE_EVENT | E45: 愛車十萬公里大保養 | G45: 技師搖頭的樣子，比報價單還貴。 | H45: 資產要維護，生活工具也要。折舊是看不見的月支出。 | I45: 現金 -45 對象:自己（大保養與換件） | Z45: outer.json
A46: OUTER_LIFE | B46: OL_D03 | C46: LIFE_EVENT | E46: 植牙自費療程 | G46: 牙醫說：這顆保不住了。 | H46: 健保之外的自費醫療，是中年後最常見的財務突襲。 | I46: 現金 -60 對象:自己（植牙自費） | X46: medical、insurable | Z46: outer.json
A47: OUTER_LIFE | B47: OL_D04 | C47: LIFE_EVENT | E47: 房屋稅＋地價稅季 | G47: 持有資產的人，才收得到這種信。 | H47: 持有成本：資產越多、稅單越厚，這是被動收入的固定摩擦。 | I47: 現金 -40 對象:自己（持有稅負） | Z47: outer.json
A48: OUTER_LIFE | B48: OL_D05 | C48: LIFE_EVENT | E48: 姪女的喜酒紅包 | G48: 長輩桌，紅包厚度就是輩分。 | H48: 人情往來是預算科目，不是意外。 | I48: 現金 -22 對象:自己（紅包與治裝） | Z48: outer.json
A49: OUTER_LIFE | B49: OL_D06 | C49: LIFE_EVENT | E49: 冰箱冷氣一起罷工 | G49: 家電有默契，總是揪團壞。 | H49: 耐久財的更換週期會重疊——備一筆家庭設備金。 | I49: 現金 -55 對象:自己（家電汰換） | Z49: outer.json
A50: OUTER_LIFE | B50: OL_L01 | C50: LIFESTYLE | E50: 頭等艙環歐三週 | G50: 躺平的機票，站著的價格。 | H50: 奢侈不是罪，問題是它常在你最有錢的錯覺裡出現。 | L50: 380 | M50: 2 | N50: 是 | Z50: outer.json
A51: OUTER_LIFE | B51: OL_L02 | C51: LIFESTYLE | E51: 私廚包場宴請老友 | G51: 主廚只服務你們這一桌。 | H51: 體驗型消費的幸福感很真，帳單也很真。 | L51: 180 | M51: 1 | N51: 是 | Z51: outer.json
A52: OUTER_LIFE | B52: OL_L03 | C52: LIFESTYLE | E52: 限量腕錶入手機會 | G52: 櫃姐說：全台只有三只。 | H52: 「稀有」是行銷字眼，不是投資屬性。 | L52: 320 | M52: 1 | N52: 是 | Z52: outer.json
A53: OUTER_LIFE | B53: OL_L04 | C53: LIFESTYLE | E53: 郵輪套房環太平洋 | G53: 陽台外是整片海，帳單外是整片零。 | H53: 大額享受請用現金流的盈餘付，不要動到本金引擎。 | L53: 450 | M53: 2 | N53: 是 | Z53: outer.json
A54: OUTER_LIFE | B54: OL_L05 | C54: LIFESTYLE | E54: 私人俱樂部會籍 | G54: 入會費只是門票，月費才是人生。 | H54: 排場稅：一次性花費會結束，每月固定支出不會。 | L54: 120 | M54: 1 | N54: 是 | Z54: outer.json
A55: OUTER_LIFE | B55: OL_V01 | C55: TAPESTRY | D55: TRIAL | E55: 朋友起鬨合資遊艇 | G55: 「你現在財務自由欸，這點錢算什麼？」 | H55: 好大喜功的錢多半不是自己想花的，是被氣氛花掉的。 | K55: axis：TEMPER｜ threshold：2｜ above：你笑著說改天先租一天試試，話題就過了。｜ below：面子上掛不住，你簽了合資意向書。｜現金 -380 對象:自己（遊艇合資款） | Z55: outer.json
A56: OUTER_LIFE | B56: OL_V02 | C56: TAPESTRY | D56: TRIAL | E56: 同學會全場我買單 | G56: 二十年沒見，誰都不想輸。 | H56: 跟過去的自己比，不要跟同學的排場比。 | K56: axis：TEMPER｜ threshold：2｜ above：你點到為止，各付各的也聊得盡興。｜ below：一句「今晚我請」，整層樓的酒都上了。｜現金 -150 對象:自己（全場買單） | Z56: outer.json
A57: OUTER_LIFE | B57: OL_V03 | C57: TAPESTRY | D57: TRIAL | E57: 網紅朋友的豪宅喬遷趴 | G57: 伴手禮的行情，是用背景牆決定的。 | H57: 社交通膨：圈子越亮，跟著亮的是你的支出。 | K57: axis：TEMPER｜ threshold：2｜ above：你帶了誠意剛好的禮，賓主盡歡。｜ below：你訂了整箱年份香檳外加名牌家電。｜現金 -220 對象:自己（排場伴手禮） | Z57: outer.json
A58: OUTER_LIFE | B58: OL_S01 | C58: TAPESTRY | D58: TRIAL | E58: 保證月配 8% 的海外基金 | G58: 「名額只留給像您這樣的高資產客戶。」 | H58: 報酬高得不合理，就是風險高得不合理——世上沒有保證 8%。 | K58: axis：PRUDENCE｜ threshold：2｜ above：你問他金管會核備字號，對方已讀不回。｜ below：你匯了款，網站三週後打不開。｜現金 -400 對象:自己（投資詐騙損失） | Z58: outer.json
A59: OUTER_LIFE | B59: OL_S02 | C59: TAPESTRY | D59: TRIAL | E59: 銀行來電：帳戶需要升級 VIP | G59: 對方連你上一筆消費都說得出來。 | H59: 真的銀行不會電話裡要你操作轉帳。掛掉，打 165。 | K59: axis：PRUDENCE｜ threshold：2｜ above：你掛斷回撥官方客服，確認是詐騙。｜ below：你照著指示到 ATM「解除設定」。｜現金 -250 對象:自己（轉帳詐騙損失） | Z59: outer.json
A60: OUTER_LIFE | B60: OL_S03 | C60: TAPESTRY | D60: TRIAL | E60: 老同學的元宇宙土地案 | G60: 「早期投資人已經翻了五倍。」 | H60: 熟人推薦是詐騙最好的包裝紙；查證對事不對人。 | K60: axis：PRUDENCE｜ threshold：2｜ above：你要白皮書和地政資料，他開始顧左右而言他。｜ below：看在交情，你投了一個單位。｜現金 -300 對象:自己（虛擬資產詐騙） | Z60: outer.json
A61: OUTER_LIFE | B61: OL_H01 | C61: LIFE_EVENT | E61: 健檢紅字：確診初期癌症 | G61: 醫師說發現得早，但治療不能等。 | H61: 重大傷病是財務自由最大的壓力測試——現金墊要扛得住自費療程加上停下來的日子。 | I61: 現金 -500 對象:自己（自費標靶療程）；停走 2 輪 對象:自己（入院治療）；每月支出（限時） +25 持續 6 輪 對象:自己（療程與看護） | X61: medical、insurable | Z61: outer.json
A62: OUTER_LIFE | B62: OL_H02 | C62: LIFE_EVENT | E62: 縱走山徑重摔 | G62: 直升機的聲音越近，帳單越厚。 | H62: 追夢的路上也要買得起意外——體力與現金墊都是裝備。 | I62: 現金 -350 對象:自己（手術與復健）；停走 2 輪 對象:自己（臥床復健）；每月支出（限時） +15 持續 4 輪 對象:自己（復健療程） | X62: accident、insurable | Z62: outer.json
A63: OUTER_LIFE | B63: OL_G01 | C63: LIFE_EVENT | E63: 舊藏字畫拍出高價 | G63: 當年隨手買的，如今是「早期眼光」。 | H63: 流動性差的收藏偶爾也會開花，但別把它當理財主軸。 | I63: 現金 +180 對象:自己（拍賣所得） | Z63: outer.json
A64: OUTER_LIFE | B64: OL_G02 | C64: LIFE_EVENT | E64: 年輕時投資的樂團爆紅 | G64: 版稅條款當年只是義氣，現在是被動收入。 | H64: 早年播的種，有些真的會發芽。 | I64: 現金 +120 對象:自己（版稅分潤） | Z64: outer.json

Sheet 生活消費卡
A1: FinFlow 內容盤點｜生活消費卡
A2: LIFESTYLE 24 張：踩到生活格抽。可選＝玩家可拒買；非可選＝直接扣款。金額單位＝千元。
A4: id | B4: 標題 | C4: 一次費用 | D4: 每月支出 | E4: 可選 | F4: 需要小孩 | G4: 情境 | H4: 教育註記 | I4: 標籤 | J4: 模組 | K4: 來源檔
A5: LS01 | B5: 最新款手機 | C5: 32 | D5: 0 | E5: 是 | G5: 舊的還能用，但新的會拍星星。 | H5: 想要與需要的差別，通常只有 24 小時的耐心。 | I5: want | K5: base.json
A6: LS02 | B6: 健身房兩年約 | C6: 8 | D6: 3 | E6: 是 | G6: 教練說現在辦最划算。 | H6: 長約把一次性決定變成每月支出，簽名前先乘以 24。 | I6: want、recurring | K6: base.json
A7: LS03 | B7: 機車定期保養 | C7: 6 | D7: 0 | E7: 否 | G7: 該換的還是要換。 | H7: 預期得到的維護費用不叫意外，叫預算。 | I7: need | K7: base.json
A8: LS04 | B8: 朋友婚禮紅包月 | C8: 12 | D8: 0 | E8: 否 | G8: 這個月有三場。 | H8: 人情支出可以預測，卻最常被漏編列。 | I8: need | K8: base.json
A9: LS05 | B9: 養一隻狗 | C9: 15 | D9: 4 | E9: 是 | G9: 牠在收容所看著你。 | H9: 養寵物是一筆十五年的月支出承諾。 | I9: want、recurring | K9: base.json
A10: LS06 | B10: 串流平台四台全開 | C10: 2 | D10: 2 | E10: 是 | G10: 每台都有想看的。 | H10: 小額訂閱的殺傷力在於你不會取消它。 | I10: want、recurring | K10: base.json
A11: LS07 | B11: 日本自由行 | C11: 45 | D11: 0 | E11: 是 | G11: 機票剛好特價。 | H11: 旅行是好事，用現金流買比用信用卡買更好。 | I11: want | K11: base.json
A12: LS08 | B12: 家電同時陣亡 | C12: 38 | D12: 0 | E12: 否 | G12: 冰箱跟冷氣講好的。 | H12: 這就是為什麼要有緊急預備金。 | I12: need | K12: base.json
A13: LS09 | B13: 牙齒治療 | C13: 25 | D13: 0 | E13: 否 | G13: 拖了半年的那顆。 | H13: 健康支出拖越久越貴，這是負利率的支出。 | I13: insurable、need、health、medical | K13: base.json
A14: LS10 | B14: 換季治裝 | C14: 10 | D14: 0 | E14: 是 | G14: 衣櫃裡永遠少一件。 | H14: 固定小額支出乘以十二，才是它真正的價格。 | I14: want | K14: base.json
A15: LS11 | B15: 車險與燃料稅 | C15: 18 | D15: 0 | E15: 否 | G15: 每年這個時候。 | H15: 年繳費用要除以十二放進月支出，才看得到真實成本。 | I15: need | K15: base.json
A16: LS12 | B16: 補習班學費 | C16: 20 | D16: 0 | E16: 否 | F16: 是 | G16: 別人的孩子都在補。 | H16: 教育投資也是支出，重點是它有沒有你要的回報。 | I16: need、family | K16: base.json
A17: LS13 | B17: 社區管理費調漲 | C17: 0 | D17: 2 | E17: 否 | G17: 公告貼在電梯裡。 | H17: 住的成本會自己長大，投資的現金流不會自動跟上。 | I17: need、recurring | K17: base.json
A18: LS14 | B18: 手沖咖啡全套 | C18: 14 | D18: 0 | E18: 是 | G18: 從此不用外帶咖啡了（真的嗎）。 | H18: 用一次性支出換未來省錢，先算清楚要幾杯才回本。 | I18: want | K18: base.json
A19: LS16 | B19: 線上課程年費 | C19: 16 | D19: 0 | E19: 是 | G19: 買了就等於學會了。 | H19: 買課的當下最有動力，續訂前先看看你上了幾堂。 | I19: want | K19: base.json
A20: LS17 | B20: 養兩隻鸚鵡 | C20: 18 | D20: 2 | E20: 是 | G20: 會學你講話，也會啃你的傢俱。 | H20: 寵物是十幾年的承諾：飼料、玩具、獸醫，每月都在帳上。 | I20: want、recurring、pet | K20: base.json
A21: LS18 | B21: 手遊限定轉蛋課金 | C21: 12 | D21: 0 | E21: 是 | G21: 保底就在下一抽，機率寫在最下面一行。 | H21: 課金買的是機率，不是結果——期望值先算再刷。 | I21: want、game | K21: base.json
A22: LS19 | B22: KTV 包廂歡唱夜 | C22: 6 | D22: 0 | E22: 是 | G22: 切歌切到凌晨兩點，隔天嗓子啞掉。 | H22: 娛樂支出沒有錯，錯的是每次都「難得嘛」。 | I22: want、social | K22: base.json
A23: LS20 | B23: 飛海外看偶像演唱會 | C23: 55 | D23: 0 | E23: 是 | G23: 機票加門票加周邊，青春無價但刷卡有價。 | H23: 為熱愛花錢可以，用循環利息付熱愛不行。 | I23: want、travel | K23: base.json
A24: LS21 | B24: 社團慶功宴 | C24: 8 | E24: 否 | F24: 是 | G24: 孩子在校際比賽得獎，全隊一起吃火鍋慶祝，家長分攤餐費。 | H24: 孩子成長中的同儕社交與成就感，是千金難買的人生回憶。 | K24: base.json
A25: LS22 | B25: 校外教學與畢業紀念冊 | C25: 12 | E25: 否 | F25: 是 | G25: 三天的校外教學行程加上厚厚的精裝紀念冊，留下青春紀錄。 | H25: 學校常態性的大額專案支出，考驗家庭短期週轉金的彈性。 | K25: base.json
A26: LS23 | B26: 孩子樂器採購與才藝比賽 | C26: 35 | E26: 否 | F26: 是 | G26: 換上高階演奏級樂器，並報名全國音樂比賽。 | H26: 才藝教育的設備升級費用往往驚人，需要與家庭財務總體目標取得平衡。 | K26: base.json
A27: LS24 | B27: 暑期夏令營體驗 | C27: 25 | E27: 否 | F27: 是 | G27: 雙薪家庭暑假無暇照顧，送孩子參加全美語戶外探索夏令營。 | H27: 暑期安親與營隊費用是現代雙薪家長每年固定的現金流重擔。 | K27: base.json
A28: LS25 | B28: 大學開學生活準備金 | C28: 50 | E28: 否 | F28: 是 | G28: 孩子考上外縣市大學，採購筆電、機車與外宿日常用品。 | H28: 子女邁入成年自立前夕，是父母家庭教育資金支出的最高峰。 | K28: base.json

Sheet 市場與總經卡
A1: FinFlow 內容盤點｜市場與總經卡
A2: MARKET 12 張（踩市場格）＋ MACRO_EVENT 20 張（景氣階段轉換時抽的政策／黑天鵝／台灣案例事件）。
A4: 牌堆 | B4: id | C4: 類型 | D4: 標題 | E4: 副標 | F4: 情境 | G4: 教育註記 | H4: 效果 | I4: 適用景氣階段 | J4: 優先序 | K4: 災難 | L4: 標籤 | M4: 模組 | N4: 來源檔
A5: MARKET | B5: MK01 | C5: MARKET | D5: 房市買氣回升 | F5: 仲介電話開始響了。 | G5: 估值上升不等於現金流上升，賣掉才算數。 | H5: 資產市值× ×1.12 持續 None 輪 限:{"kind": "REALESTATE"}（房市回升） | L5: housing | N5: base.json
A6: MARKET | B6: MK02 | C6: MARKET | D6: 房市急凍 | F6: 待售物件掛了半年。 | G6: 資產價格會跌，但貸款餘額不會跟著跌。 | H6: 資產市值× ×0.9 持續 None 輪 限:{"kind": "REALESTATE"}（房市急凍） | L6: housing | N6: base.json
A7: MARKET | B7: MK03 | C7: MARKET | D7: 出售窗口：房市過熱 | F7: 有人開高價要你手上的物件。 | G7: 高點出場是紀律，不是運氣。 | H7: 限時賣價 限:{"kind": "REALESTATE"}（房產高價收購） | L7: housing | N7: base.json
A8: MARKET | B8: MK04 | C8: MARKET | D8: 觀光潮帶動小店營收 | F8: 排隊排到巷口。 | G8: 景氣好的時候，事業利潤先反應。 | H8: 資產收入× ×1.3 持續 4 輪 限:{"kind": "BUSINESS"}（觀光潮） | L8: business | N8: base.json
A9: MARKET | B9: MK05 | C9: MARKET | D9: 最低工資調漲 | F9: 人事成本全面上升。 | G9: 營運成本上升會直接吃掉事業的淨利。 | H9: 資產收入× ×0.85 持續 4 輪 限:{"kind": "BUSINESS"}（人事成本上升 → 事業淨利下降） | L9: business | N9: base.json
A10: MARKET | B10: MK06 | C10: MARKET | D10: 租屋需求旺季 | F10: 看屋的人排到樓下。 | G10: 租金上漲直接進被動收入，比估值上漲實在。 | H10: 資產收入× ×1.15 持續 6 輪 限:{"kind": "REALESTATE"}（租金旺季） | L10: housing | N10: base.json
A11: MARKET | B11: MK07 | C11: MARKET | D11: 社區大樓公共修繕 | F11: 外牆磁磚要全面翻修。 | G11: 持有成本是報酬率的隱形殺手。 | H11: 現金 -8 對象:全體 限:{"kind": "REALESTATE"}（修繕分攤） | L11: housing | N11: base.json
A12: MARKET | B12: MK08 | C12: MARKET | D12: 外送平台抽成調高 | F12: 平台單方面通知。 | G12: 依賴單一通路的生意，議價權不在你手上。 | H12: 資產收入× ×0.9 持續 3 輪 限:{"kind": "BUSINESS"}（通路抽成調高 → 事業淨利下降） | L12: business | N12: base.json
A13: MARKET | B13: MK09 | C13: MARKET | D13: 科技股法說會利多 | F13: 開盤跳空。 | G13: 股價上漲時最危險的念頭是「再等一下」。 | H13: 股價 ×1.35 STK_TECH（科技股大漲） | L13: equity | M13: M1 | N13: base.json
A14: MARKET | B14: MK10 | C14: MARKET | D14: 外資大舉調節 | F14: 連五天賣超。 | G14: 下跌時檢查的是你的成本與現金流，不是新聞。 | H14: 股價 ×0.72 STK_TECH（科技股重挫） | L14: equity | M14: M1 | N14: base.json
A15: MARKET | B15: MK11 | C15: MARKET | D15: 高股息族群配息加發 | F15: 本期配息優於預期。 | G15: 配息是現金流，這才是被動收入的來源。 | H15: 股息加成 ×2 STK_DIV（配息加發） | L15: equity、dividend | M15: M1 | N15: base.json
A16: MARKET | B16: MK12 | C16: MARKET | D16: 小型股崩跌 | F16: 消息面破功。 | G16: 高波動的另一面永遠是高風險，兩者不能分開買。 | H16: 股價 ×0.55 STK_SPEC（小型股崩跌） | L16: equity、speculative | M16: M1 | N16: base.json
A17: MACRO_EVENT | B17: MA01 | C17: MACRO | D17: 央行祭出信用管制 | F17: 第七波，這次連第二戶都限。 | G17: 政策一改，你能借到的錢就變少——槓桿不是永遠都在。 | H17: 改參數 maxLTV=0.5 持續 8 輪（信用管制） | I17: BOOM | J17: 90 | N17: m4.json
A18: MACRO_EVENT | B18: MA02 | C18: MACRO | D18: 青年購屋利息補貼 | F18: 財政部說要幫年輕人一把。 | G18: 補貼會降低你的月付息，但它有到期日。 | H18: 改參數 mortgageSpread=0.009 持續 6 輪（利息補貼） | I18: RECOVERY、RECESSION | J18: 40 | N18: m4.json
A19: MACRO_EVENT | B19: MA03 | C19: MACRO | D19: 科技業大規模裁員 | F19: 公告貼在內部網站上。 | G19: 景氣反轉時，主動收入是最脆弱的那一項。 | H19: 格子效果× ×2 持續 4 輪 LAYOFF（裁員潮） | I19: RECESSION、DEPRESSION | J19: 60 | N19: m4.json
A20: MACRO_EVENT | B20: MA04 | C20: MACRO | D20: 出口接單暢旺 | F20: 貨櫃排到下個月。 | G20: 景氣好的時候，先反應的是事業利潤而不是薪水。 | H20: 資產收入× ×1.3 持續 4 輪 對象:全體 限:{"kind": "BUSINESS"}（出口暢旺） | I20: RECOVERY、BOOM | J20: 30 | N20: m4.json
A21: MACRO_EVENT | B21: MA05 | C21: MACRO | D21: 通膨升溫，物價全面上漲 | F21: 便當又漲了十塊。 | G21: 通膨會同時墊高你的支出與自由門檻。 | H21: 每月支出（限時） +4 持續 6 輪 對象:全體（物價上漲） | I21: BOOM | J21: 50 | N21: m4.json
A22: MACRO_EVENT | B22: MA06 | C22: MACRO | D22: 租金補貼擴大辦理 | F22: 房客申請通過了。 | G22: 補貼流向房客，但收租方的空置率會下降。 | H22: 資產收入× ×1.08 持續 6 輪 對象:全體 限:{"kind": "REALESTATE"}（租金補貼） | I22: RECESSION、DEPRESSION | J22: 20 | N22: m4.json
A23: MACRO_EVENT | B23: MA07 | C23: MACRO | D23: 銀行全面緊縮授信 | F23: 行員說今年額度用完了。 | G23: 流動性收縮時，好機會反而最多——前提是你手上有現金。 | H23: 改參數 maxLTV=0.6 持續 5 輪（授信緊縮）；改參數 cashoutLTV=0.5 持續 5 輪（增貸緊縮） | I23: RECESSION、DEPRESSION | J23: 80 | N23: m4.json
A24: MACRO_EVENT | B24: MA08 | C24: MACRO | D24: 股市當沖降稅延長 | F24: 成交量放大。 | G24: 交易成本下降會讓人交易更頻繁，這通常不是好事。 | H24: 改參數 stockVolatilityMult=1.4 持續 5 輪（量能放大） | I24: BOOM、RECOVERY | J24: 10 | N24: m4.json
A25: MACRO_EVENT | B25: MA09 | C25: MACRO | D25: 強震來襲，老屋受損 | F25: 凌晨的搖晃把所有人搖醒，牆上多了一道裂縫。 | G25: 天災不挑景氣。緊急預備金與保險，是唯一能提前做的事。 | H25: 現金 -35 對象:全體（修繕與停業損失）；資產市值× ×0.9 對象:全體 限:{"kind": "REALESTATE"}（房屋受損跌價） | J25: 95 | K25: 是 | N25: m4.json
A26: MACRO_EVENT | B26: MA10 | C26: MACRO | D26: 強颱過境，全台停班停市 | F26: 風雨假放了兩天，鐵皮屋頂飛了一片。 | G26: 對做生意的人，停業一天就是負現金流一天。 | H26: 現金 -18 對象:全體（防災與災後清理）；資產收入× ×0.75 持續 3 輪 對象:全體 限:{"kind": "BUSINESS"}（停業影響） | J26: 85 | K26: 是 | N26: m4.json
A27: MACRO_EVENT | B27: MA11 | C27: MACRO | D27: 豪雨土石流，山區聯外中斷 | F27: 新聞畫面裡，整條路變成了河。 | G27: 供應鏈斷一段，物價就漲一波——災害的帳單常常晚幾個月才到。 | H27: 現金 -12 對象:全體（物資與交通損失）；每月支出（限時） +3 持續 4 輪 對象:全體（物流成本上升） | J27: 70 | K27: 是 | N27: m4.json
A28: MACRO_EVENT | B28: MA12 | C28: MACRO | D28: 銀行大舉抽銀根 | F28: 通知書寫著：additional collateral required。 | G28: 銀行雨天收傘是常態。槓桿開滿的人，第一滴雨就出局。 | H28: 改參數 maxLTV=0.4 持續 6 輪（抽銀根）；改參數 cashoutLTV=0.3 持續 6 輪（增貸凍結）；改參數 stockVolatilityMult=1.5 持續 6 輪（市場動盪） | I28: RECESSION、DEPRESSION | J28: 92 | N28: m4.json
A29: MACRO_EVENT | B29: MA13 | C29: MACRO | D29: 金融風暴，資產全面重挫 | F29: 開盤十分鐘，跌幅榜整片同一個顏色。 | G29: 系統性風險來的時候，「分散」救不了你，「現金與低槓桿」才行。 | H29: 資產市值× ×0.85 對象:全體 限:{"kind": "REALESTATE"}（不動產重挫）；資產收入× ×0.8 持續 4 輪 對象:全體 限:{"kind": "BUSINESS"}（消費急凍）；改參數 stockVolatilityMult=1.8 持續 6 輪（市場恐慌） | I29: DEPRESSION | J29: 99 | N29: m4.json
A30: MACRO_EVENT | B30: MKT_BODA_FRAUD | C30: MACRO_EVENT | D30: 科技股王審計假帳風暴 | E30: 名牌科技股被爆透過海外子公司虛增營收，引發市場恐慌拋售。 | F30: 財經雜誌剛封他為年度典範，隔週公司突然宣布帳上數十億現金全在海外凍結（歷史原型：博達案）。 | G30: 營收會騙人、獲利會造假，唯有真正的現金流量表騙不了人。 | H30: 股價 ×0.6 STK_TECH（假帳風暴） | N30: m4.json
A31: MACRO_EVENT | B31: MKT_TAIDIAN_DELIST | C31: MACRO_EVENT | D31: 老牌權值股黑天鵝掏空 | E31: 老牌權值傳產龍頭爆發高達兩百億掏空弊案，股票淪為壁紙停止交易。 | F31: 爸媽存了一輩子的傳產龍頭股，一夕之間爆出海外兩百億黑洞（歷史原型：太電案）。 | G31: 資產規模大不代表不會倒，公司治理與內部稽核才是資產的防腐劑。 | H31: 股價 ×0.5 STK_DIV（掏空弊案） | N31: m4.json
A32: MACRO_EVENT | B32: MACRO_DUAL_CARD_CRISIS | C32: MACRO_EVENT | D32: 全台信用緊縮與雙卡風暴 | E32: 高利現金卡違約潮引發銀行全面收緊信貸，消費貸利率調升至上限。 | F32: 借錢是件快樂的事——直到帳單上的循環利率跳到 18%（歷史原型：雙卡風暴）。 | G32: 用短期高利消費貸去支撐生活或投資，是通往破產最快的一條路。 | H32: 改參數 creditSpread=0.11 持續 6 輪（信用緊縮）；改參數 marginSpread=0.06 持續 6 輪（信用緊縮） | N32: m4.json
A33: MACRO_EVENT | B33: MKT_BIOTECH_UNBLIND | C33: MACRO_EVENT | D33: 夢幻新藥解盲無量崩盤 | E33: 投機生技股臨床解盲未達預期，連續跌停鎖死引發融資斷頭潮。 | F33: 群組每天都在傳『解盲一定過』，賭贏翻倍、賭輸無量跌停賣都賣不掉（歷史原型：基亞浩鼎案）。 | G33: 全靠單一事件下注的投機不是投資，一旦失敗流動性直接歸零。 | H33: 股價 ×0.4 STK_SPEC（解盲失敗） | N33: m4.json
A34: MACRO_EVENT | B34: MAS01 | C34: MACRO | D34: 生成式 AI 全面進入開發流程 | F34: 你昨天寫三天的東西，它三分鐘給你一版。 | G34: 技能會折舊。真正保值的不是你學過什麼，是你還在不在學。 | H34: 技能過時 對象:全體 家族:TECH（AI 取代基礎開發） | I34: BOOM、RECOVERY | J34: 70 | M34: M8 | N34: skill.json
A35: MACRO_EVENT | B35: MAS02 | C35: MACRO | D35: 民法與稅法同步大修 | F35: 新聞跑馬燈整天在跑，事務所電話接不完。 | G35: 你以為記住的規則，其實是那一年的規則。 | H35: 技能過時 對象:全體 SKL_LAW（法規大修） | I35: BOOM、RECOVERY、RECESSION | J35: 65 | M35: M8 | N35: skill.json
A36: MACRO_EVENT | B36: MAS03 | C36: MACRO | D36: 技術士證照制度改制，舊證落日 | F36: 公告貼在工會門口，三個月內要換照。 | G36: 證照不是終身有效的護身符，是需要續期的門票。 | H36: 技能過時 對象:全體 SKL_PLUMB（舊證落日） | I36: RECOVERY、RECESSION、DEPRESSION | J36: 55 | M36: M8 | N36: skill.json

Sheet 品格帳本卡
A1: FinFlow 內容盤點｜品格帳本卡
A2: LIFE_TAPESTRY 326 張（M6 品格帳本）：修養 CULTIVATE／考驗 TRIAL／日常 DAILY 等。每局抽樣 13＋13＋10。金額單位＝千元。
A4: id | B4: 子類 | C4: 分類 | D4: 品格軸 | E4: 標題 | F4: 情境 | G4: 教育註記 | H4: 費用 | I4: 每月支出 | J4: 可選 | K4: 效果 | L4: 品格分歧（依等級） | M4: 需要小孩 | N4: 模組 | O4: 來源檔
A5: LT_C001 | B5: CULTIVATE | C5: 育樂 | D5: 情緒 | E5: 情緒管理工作坊 | F5: 六堂課，教你在爆炸前先數三秒。 | G5: 脾氣是可以練的技術，練它的錢比賠償金便宜太多。 | H5: 18 | K5: 品格 情緒+1 | N5: M6 | O5: m6.json
A6: LT_C002 | B6: CULTIVATE | C6: 育樂 | D6: 情緒 | E6: 每週晨跑習慣 | F6: 跑完那三十分鐘，很多事就沒那麼想吵。 | G6: 運動是最便宜的情緒投資。 | H6: 6 | I6: 1 | K6: 品格 情緒+1 | N6: M6 | O6: m6.json
A7: LT_C003 | B7: CULTIVATE | C7: 衣 | D7: 情緒 | E7: 斷捨離整理課 | F7: 把衣櫃清空那天，也清掉了一些焦慮。 | G7: 衝動購物常是情緒問題，不是預算問題。 | H7: 9 | K7: 品格 情緒+1 | N7: M6 | O7: m6.json
A8: LT_C004 | B8: CULTIVATE | C8: 育樂 | D8: 情緒 | E8: 正念冥想 App 年費 | F8: 每天十分鐘，學著看著念頭經過。 | G8: 覺察情緒，是不被情緒綁架的第一步。 | H8: 4 | K8: 品格 情緒+1 | N8: M6 | O8: m6.json
A9: LT_C005 | B9: CULTIVATE | C9: 食 | D9: 情緒 | E9: 戒酒三個月挑戰 | F9: 聚會改點無酒精，隔天的自己會謝謝你。 | G9: 許多失控都始於一杯下肚。 | H9: 0 | K9: 品格 情緒+1 | N9: M6 | O9: m6.json
A10: LT_C006 | B10: CULTIVATE | C10: 育樂 | D10: 情緒 | E10: 心理諮商月會 | F10: 每月一次，把積著的話說出來。 | G10: 定期清理情緒，比爆掉再收拾划算。 | H10: 0 | I10: 6 | K10: 品格 情緒+1 | N10: M6 | O10: m6.json
A11: LT_C007 | B11: CULTIVATE | C11: 住 | D11: 情緒 | E11: 打造一個獨處角落 | F11: 一張椅子、一盞燈，煩了就退到這裡。 | G11: 給情緒一個緩衝空間，衝突就少一半。 | H11: 14 | K11: 品格 情緒+1 | N11: M6 | O11: m6.json
A12: LT_C008 | B12: CULTIVATE | C12: 行 | D12: 情緒 | E12: 通勤改走風景路線 | F12: 慢個十分鐘，心情好一整天。 | G12: 把趕路的焦躁，換成可以呼吸的節奏。 | H12: 0 | I12: 2 | K12: 品格 情緒+1 | N12: M6 | O12: m6.json
A13: LT_C009 | B13: CULTIVATE | C13: 育樂 | D13: 情緒 | E13: 報名合唱團 | F13: 一起唱歌的人，比較不容易對彼此吼。 | G13: 把情緒放進不傷人的出口。 | H13: 8 | I13: 2 | K13: 品格 情緒+1 | N13: M6 | O13: m6.json
A14: LT_C010 | B14: CULTIVATE | C14: 育樂 | D14: 情緒 | E14: 寫情緒日記 | F14: 睡前三行，寫下今天最想罵人的一刻。 | G14: 寫下來，就多了一次不衝動的機會。 | H14: 2 | K14: 品格 情緒+1 | N14: M6 | O14: m6.json
A15: LT_C011 | B15: CULTIVATE | C15: 食 | D15: 情緒 | E15: 學會好好吃一頓飯 | F15: 不配手機，專心把一餐吃完。 | G15: 慢下來的胃，帶著慢下來的脾氣。 | H15: 5 | K15: 品格 情緒+1 | N15: M6 | O15: m6.json
A16: LT_C012 | B16: CULTIVATE | C16: 住 | D16: 情緒 | E16: 隔音窗簾與降噪 | F16: 把外面的吵，擋在窗戶外面。 | G16: 減少刺激源，情緒自然穩。 | H16: 22 | K16: 品格 情緒+1 | N16: M6 | O16: m6.json
A17: LT_C013 | B17: CULTIVATE | C17: 育樂 | D17: 情緒 | E17: 學一項需要專注的手作 | F17: 捏陶或木工，手忙了，腦就靜了。 | G17: 專注是情緒最好的鎮定劑。 | H17: 12 | I17: 1 | K17: 品格 情緒+1 | N17: M6 | O17: m6.json
A18: LT_C014 | B18: CULTIVATE | C18: 行 | D18: 情緒 | E18: 改騎自行車代步 | F18: 踩踏之間，把一天的悶氣蹬出去。 | G18: 規律運動長期壓低情緒的基準線。 | H18: 10 | K18: 品格 情緒+1 | N18: M6 | O18: m6.json
A19: LT_C015 | B19: CULTIVATE | C19: 育樂 | D19: 情緒 | E19: 夫妻溝通共學 | F19: 一起上課，學怎麼吵得不傷人。 | G19: 會吵架的伴侶，未必比不會和好的更糟。 | H19: 16 | K19: 品格 情緒+1 | N19: M6 | O19: m6.json
A20: LT_C016 | B20: CULTIVATE | C20: 行 | D20: 守法謹慎 | E20: 防禦駕駛課程 | F20: 教練說：路上最貴的是那零點五秒。 | G20: 用小錢買掉大額尾部風險。 | H20: 14 | K20: 品格 守法謹慎+1 | N20: M6 | O20: m6.json
A21: LT_C017 | B21: CULTIVATE | C21: 住 | D21: 守法謹慎 | E21: 居家安檢與火險規劃 | F21: 師傅說這條線再兩年會出事。 | G21: 保險把不確定的大損失換成確定的小成本。 | H21: 22 | I21: 1 | K21: 品格 守法謹慎+1 | N21: M6 | O21: m6.json
A22: LT_C018 | B22: CULTIVATE | C22: 食 | D22: 守法謹慎 | E22: 年度健檢加做項目 | F22: 多花的那幾項，醫生說值得。 | G22: 早期發現的成本，永遠低於晚期治療。 | H22: 16 | K22: 品格 守法謹慎+1 | N22: M6 | O22: m6.json
A23: LT_C019 | B23: CULTIVATE | C23: 行 | D23: 守法謹慎 | E23: 車險保障升級 | F23: 加做第三人責任險與零件險。 | G23: 保費看的是保障範圍，不是誰最便宜。 | H23: 11 | I23: 1 | K23: 品格 守法謹慎+1 | N23: M6 | O23: m6.json
A24: LT_C020 | B24: CULTIVATE | C24: 住 | D24: 守法謹慎 | E24: 地震險與颱風防護 | F24: 住在這座島，這筆不能省。 | G24: 天災不會挑你有沒有準備。 | H24: 8 | I24: 1 | K24: 品格 守法謹慎+1 | N24: M6 | O24: m6.json
A25: LT_C021 | B25: CULTIVATE | C25: 食 | D25: 守法謹慎 | E25: 食材來源與保存教學 | F25: 學會看標示、學會冷藏鏈。 | G25: 省下的是全家人的腸胃與醫藥費。 | H25: 5 | K25: 品格 守法謹慎+1 | N25: M6 | O25: m6.json
A26: LT_C022 | B26: CULTIVATE | C26: 育樂 | D26: 守法謹慎 | E26: 投資詐騙辨識課 | F26: 高報酬零風險，聽到就該轉身。 | G26: 看得懂騙局，是最高報酬的一堂課。 | H26: 6 | K26: 品格 守法謹慎+1 | N26: M6 | O26: m6.json
A27: LT_C023 | B27: CULTIVATE | C27: 住 | D27: 守法謹慎 | E27: 合約與租約審閱習慣 | F27: 簽名前，逐條看過一遍。 | G27: 一時的仔細，省下漫長的糾紛。 | H27: 4 | K27: 品格 守法謹慎+1 | N27: M6 | O27: m6.json
A28: LT_C024 | B28: CULTIVATE | C28: 行 | D28: 守法謹慎 | E28: 定期車輛保養紀錄 | F28: 小病不拖成大修。 | G28: 預防性維護的帳單，永遠比故障便宜。 | H28: 6 | I28: 2 | K28: 品格 守法謹慎+1 | N28: M6 | O28: m6.json
A29: LT_C025 | B29: CULTIVATE | C29: 住 | D29: 守法謹慎 | E29: 建立緊急預備金 | F29: 先存下六個月的生活費再說別的。 | G29: 現金是意外來臨時唯一不會背叛你的資產。 | H29: 0 | K29: 品格 守法謹慎+1 | N29: M6 | O29: m6.json
A30: LT_C026 | B30: CULTIVATE | C30: 食 | D30: 守法謹慎 | E30: 戒掉來路不明的保健品 | F30: 貴又沒用，還可能傷身。 | G30: 把錢花在證據上，不是花在恐懼上。 | H30: 0 | K30: 品格 守法謹慎+1 | N30: M6 | O30: m6.json
A31: LT_C027 | B31: CULTIVATE | C31: 育樂 | D31: 守法謹慎 | E31: 個資與資安基本功 | F31: 兩步驗證、不亂點連結。 | G31: 一次外洩，可能賠掉多年積蓄。 | H31: 3 | K31: 品格 守法謹慎+1 | N31: M6 | O31: m6.json
A32: LT_C028 | B32: CULTIVATE | C32: 住 | D32: 守法謹慎 | E32: 立好遺囑與保單受益人 | F32: 把該交代的先交代清楚。 | G32: 負責任的規劃，是留給家人的溫柔。 | H32: 10 | K32: 品格 守法謹慎+1 | N32: M6 | O32: m6.json
A33: LT_C029 | B33: CULTIVATE | C33: 行 | D33: 守法謹慎 | E33: 加裝行車記錄器 | F33: 路上的事，讓證據說話。 | G33: 一次事故，就回本了。 | H33: 7 | K33: 品格 守法謹慎+1 | N33: M6 | O33: m6.json
A34: LT_C030 | B34: CULTIVATE | C34: 食 | D34: 守法謹慎 | E34: 控制信用卡張數 | F34: 留兩張夠用，其餘剪掉。 | G34: 少一個循環利息的坑，就多一分餘裕。 | H34: 0 | K34: 品格 守法謹慎+1 | N34: M6 | O34: m6.json
A35: LT_C031 | B35: CULTIVATE | C35: 育樂 | D35: 教養 | E35: 親子露營三天 | F35: 沒訊號的兩晚，他跟你講了很多話。 | G35: 陪伴是教養裡最無法外包的一項。 | H35: 12 | K35: 品格 教養+1 | M35: 是 | N35: M6 | O35: m6.json
A36: LT_C032 | B36: CULTIVATE | C36: 育樂 | D36: 教養 | E36: 陪練才藝半年 | F36: 每週兩次接送，你在教室外看完三本書。 | G36: 教養的投入常是時間，不只是學費。 | H36: 10 | I36: 5 | K36: 品格 教養+1 | M36: 是 | N36: M6 | O36: m6.json
A37: LT_C033 | B37: CULTIVATE | C37: 育樂 | D37: 教養 | E37: 親職溝通講座 | F37: 講師說：先聽完，再回話。 | G37: 教養方法可以學，學了的人少走冤枉路。 | H37: 7 | K37: 品格 教養+1 | M37: 是 | N37: M6 | O37: m6.json
A38: LT_C034 | B38: CULTIVATE | C38: 食 | D38: 教養 | E38: 一起下廚的週末 | F38: 切菜洗米之間，聊了學校的事。 | G38: 共做一件事，比一百句叮嚀更靠近。 | H38: 4 | K38: 品格 教養+1 | M38: 是 | N38: M6 | O38: m6.json
A39: LT_C035 | B39: CULTIVATE | C39: 育樂 | D39: 教養 | E39: 給孩子的第一個帳戶 | F39: 教他把零用錢分成花、存、給。 | G39: 金錢觀是教出來的，不是等帳單來教的。 | H39: 5 | K39: 品格 教養+1 | M39: 是 | N39: M6 | O39: m6.json
A40: LT_C036 | B40: CULTIVATE | C40: 住 | D40: 教養 | E40: 佈置孩子的讀書角 | F40: 一張好桌燈，一個屬於他的位置。 | G40: 環境會偷偷替你完成一半的教養。 | H40: 14 | K40: 品格 教養+1 | M40: 是 | N40: M6 | O40: m6.json
A41: LT_C037 | B41: CULTIVATE | C41: 行 | D41: 教養 | E41: 一起完成一趟長途旅行 | F41: 計畫、迷路、再一起找到路。 | G41: 一起解決問題，是最好的身教。 | H41: 30 | K41: 品格 教養+1 | M41: 是 | N41: M6 | O41: m6.json
A42: LT_C038 | B42: CULTIVATE | C42: 育樂 | D42: 教養 | E42: 陪讀睡前故事習慣 | F42: 每晚十五分鐘，雷打不動。 | G42: 穩定的陪伴，長成孩子的安全感。 | H42: 0 | I42: 1 | K42: 品格 教養+1 | M42: 是 | N42: M6 | O42: m6.json
A43: LT_C039 | B43: CULTIVATE | C43: 育樂 | D43: 教養 | E43: 支持孩子的興趣試錯 | F43: 讓他學、也讓他放棄，再學別的。 | G43: 允許試錯，才養得出會選擇的人。 | H43: 9 | I43: 3 | K43: 品格 教養+1 | M43: 是 | N43: M6 | O43: m6.json
A44: LT_C040 | B44: CULTIVATE | C44: 食 | D44: 教養 | E44: 家庭固定共餐時間 | F44: 再忙，一週也要一起吃幾頓。 | G44: 餐桌是家庭最日常的教室。 | H44: 0 | I44: 2 | K44: 品格 教養+1 | M44: 是 | N44: M6 | O44: m6.json
A45: LT_C041 | B45: CULTIVATE | C45: 育樂 | D45: 教養 | E45: 陪孩子當志工一天 | F45: 去一次才知道自己有多幸運。 | G45: 同理心不是講的，是帶著去看見的。 | H45: 3 | K45: 品格 教養+1 | M45: 是 | N45: M6 | O45: m6.json
A46: LT_C042 | B46: CULTIVATE | C46: 育樂 | D46: 教養 | E46: 和青春期孩子的定期約會 | F46: 一杯飲料的時間，只聽不評。 | G46: 青春期需要的是陪伴，不是保證金。 | H46: 6 | I46: 1 | K46: 品格 教養+1 | M46: 是 | N46: M6 | O46: m6.json
A47: LT_C043 | B47: CULTIVATE | C47: 孝親家庭 | D47: 孝親 | E47: 父母生日紅包 | F47: 媽媽嘴上說不用，紅包收得很快。 | G47: 孝順的錢不求回報，但會回到你的生活裡。 | H47: 10 | K47: 品格 孝親+1 | N47: M6 | O47: m6.json
A48: LT_C044 | B48: CULTIVATE | C48: 孝親家庭 | D48: 孝親 | E48: 帶父母出國一趟 | F48: 他們一路拍照，回來洗了三本相簿。 | G48: 這筆錢沒有報酬率，但有到期日。 | H48: 80 | K48: 品格 孝親+1 | N48: M6 | O48: m6.json
A49: LT_C045 | B49: CULTIVATE | C49: 孝親家庭 | D49: 孝親 | E49: 每月固定孝親金 | F49: 轉帳設成自動的，就不會忘。 | G49: 固定的小額，比偶爾的大額更能支撐一個家。 | H49: 0 | I49: 6 | K49: 品格 孝親+1 | N49: M6 | O49: m6.json
A50: LT_C046 | B50: CULTIVATE | C50: 孝親家庭 | D50: 孝親 | E50: 老家浴室做防滑 | F50: 這個年紀跌一次很麻煩。 | G50: 預防性的支出，往往是最划算的孝順。 | H50: 40 | K50: 品格 孝親+1 | N50: M6 | O50: m6.json
A51: LT_C047 | B51: CULTIVATE | C51: 孝親家庭 | D51: 孝親 | E51: 陪回診半天 | F51: 你只是坐在旁邊，他一路講你小時候。 | G51: 孝順很多時候只是到場。 | H51: 3 | K51: 品格 孝親+1 | N51: M6 | O51: m6.json
A52: LT_C048 | B52: CULTIVATE | C52: 孝親家庭 | D52: 孝親 | E52: 替父母加保醫療險 | F52: 趁還能保的時候先保起來。 | G52: 晚一年，可能就保不進去了。 | H52: 0 | I52: 8 | K52: 品格 孝親+1 | N52: M6 | O52: m6.json
A53: LT_C049 | B53: CULTIVATE | C53: 孝親家庭 | D53: 孝親 | E53: 教爸媽用智慧手機 | F53: 從視訊開始，世界就近了。 | G53: 陪伴不只給錢，也給他們跟上時代的能力。 | H53: 2 | K53: 品格 孝親+1 | N53: M6 | O53: m6.json
A54: LT_C050 | B54: CULTIVATE | C54: 孝親家庭 | D54: 孝親 | E54: 家族年度聚餐基金 | F54: 訂個好餐廳，讓長輩當主角。 | G54: 把家人聚在一起，本身就有價值。 | H54: 15 | K54: 品格 孝親+1 | N54: M6 | O54: m6.json
A55: LT_C051 | B55: CULTIVATE | C55: 孝親家庭 | D55: 孝親 | E55: 替老家換新家電 | F55: 那台冰箱比你年紀還大了。 | G55: 孝順也可以很實際。 | H55: 22 | K55: 品格 孝親+1 | N55: M6 | O55: m6.json
A56: LT_C052 | B56: CULTIVATE | C56: 孝親家庭 | D56: 孝親 | E56: 固定回家陪吃飯 | F56: 每週一次，讓廚房又熱鬧起來。 | G56: 時間是父母最想要、也最買不到的禮物。 | H56: 0 | I56: 3 | K56: 品格 孝親+1 | N56: M6 | O56: m6.json
A57: LT_C053 | B57: CULTIVATE | C57: 孝親家庭 | D57: 孝親 | E57: 替父母規劃退休現金流 | F57: 陪他們把保單與存款盤一次。 | G57: 孝順的最高段，是讓他們不必依賴誰。 | H57: 6 | K57: 品格 孝親+1 | N57: M6 | O57: m6.json
A58: LT_C054 | B58: CULTIVATE | C58: 孝親家庭 | D58: 孝親 | E58: 照顧者喘息服務 | F58: 請人幫忙半天，讓自己也能喘口氣。 | G58: 照顧者先顧好自己，才顧得久。 | H58: 0 | I58: 5 | K58: 品格 孝親+1 | N58: M6 | O58: m6.json
A59: LT_C055 | B59: CULTIVATE | C59: 育樂 | D59: 情緒 | E59: 數位排毒週末 | F59: 關掉通知那兩天，心跳都慢了下來。 | G59: 資訊過載是這時代的隱形壓力源。 | H59: 6 | K59: 品格 情緒+1 | N59: M6 | O59: m6.json
A60: LT_C056 | B60: CULTIVATE | C60: 住 | D60: 情緒 | E60: 替家裡添點綠意 | F60: 照顧植物的人，比較有耐心。 | G60: 把注意力放在會生長的東西上，情緒也長得好。 | H60: 5 | K60: 品格 情緒+1 | N60: M6 | O60: m6.json
A61: LT_C057 | B61: CULTIVATE | C61: 育樂 | D61: 情緒 | E61: 學會拒絕的練習課 | F61: 把「不」說出口，比想像中輕鬆。 | G61: 守住界線，是情緒穩定的地基。 | H61: 7 | K61: 品格 情緒+1 | N61: M6 | O61: m6.json
A62: LT_C058 | B62: CULTIVATE | C62: 行 | D62: 情緒 | E62: 開車時聽有聲書 | F62: 塞車也能變成充電的時間。 | G62: 把等待重新定義，怒氣就少了出口。 | H62: 0 | I62: 1 | K62: 品格 情緒+1 | N62: M6 | O62: m6.json
A63: LT_C059 | B63: CULTIVATE | C63: 食 | D63: 情緒 | E63: 週末不喝含糖飲料 | F63: 血糖穩，脾氣也穩。 | G63: 身體的平衡，撐著情緒的平衡。 | H63: 2 | K63: 品格 情緒+1 | N63: M6 | O63: m6.json
A64: LT_C060 | B64: CULTIVATE | C64: 育樂 | D64: 情緒 | E64: 固定的睡眠儀式 | F64: 睡飽的人，世界都比較友善。 | G64: 睡眠債會用壞脾氣來討。 | H64: 3 | K64: 品格 情緒+1 | N64: M6 | O64: m6.json
A65: LT_C061 | B65: CULTIVATE | C65: 住 | D65: 情緒 | E65: 把爭吵留在客廳外 | F65: 臥室只留給休息與和好。 | G65: 為情緒設好場所的界線。 | H65: 0 | K65: 品格 情緒+1 | N65: M6 | O65: m6.json
A66: LT_C062 | B66: CULTIVATE | C66: 食 | D66: 守法謹慎 | E66: 建立食物過敏紀錄 | F66: 家人吃了什麼、有無反應，都寫下來。 | G66: 紀錄讓風險看得見、可預防。 | H66: 2 | K66: 品格 守法謹慎+1 | N66: M6 | O66: m6.json
A67: LT_C063 | B67: CULTIVATE | C67: 住 | D67: 守法謹慎 | E67: 定期檢查保單內容 | F67: 保障夠不夠、有沒有重複，一年看一次。 | G67: 買了不看的保單，等於沒買。 | H67: 0 | K67: 品格 守法謹慎+1 | N67: M6 | O67: m6.json
A68: LT_C064 | B68: CULTIVATE | C68: 行 | D68: 守法謹慎 | E68: 出遠門前的車況檢查 | F68: 胎壓、機油、雨刷，五分鐘的事。 | G68: 預防的五分鐘，勝過路邊的五小時。 | H68: 3 | K68: 品格 守法謹慎+1 | N68: M6 | O68: m6.json
A69: LT_C065 | B69: CULTIVATE | C69: 育樂 | D69: 守法謹慎 | E69: 分散帳戶與提款上限 | F69: 把雞蛋放不同籃子，也設好破口。 | G69: 控管損失上限，是資安的基本功。 | H69: 0 | K69: 品格 守法謹慎+1 | N69: M6 | O69: m6.json
A70: LT_C066 | B70: CULTIVATE | C70: 住 | D70: 守法謹慎 | E70: 社區逃生路線演練 | F70: 真的走一次，才知道哪裡卡。 | G70: 演練過的安全，才是真的安全。 | H70: 0 | K70: 品格 守法謹慎+1 | N70: M6 | O70: m6.json
A71: LT_C067 | B71: CULTIVATE | C71: 食 | D71: 守法謹慎 | E71: 建立家庭急救箱 | F71: 過期的藥先換掉，缺的補齊。 | G71: 關鍵時刻，準備決定結果。 | H71: 4 | K71: 品格 守法謹慎+1 | N71: M6 | O71: m6.json
A72: LT_C068 | B72: CULTIVATE | C72: 行 | D72: 守法謹慎 | E72: 保留重要文件備份 | F72: 證件、保單、契約掃描存雲端。 | G72: 一場水災或火災，考驗你的備份。 | H72: 2 | K72: 品格 守法謹慎+1 | N72: M6 | O72: m6.json
A73: LT_C069 | B73: CULTIVATE | C73: 育樂 | D73: 教養 | E73: 陪孩子做一次預算 | F73: 一起把零用錢分成花存給。 | G73: 財商是陪出來的，不是講出來的。 | H73: 3 | K73: 品格 教養+1 | M73: 是 | N73: M6 | O73: m6.json
A74: LT_C070 | B74: CULTIVATE | C74: 食 | D74: 教養 | E74: 教孩子下一道拿手菜 | F74: 會照顧自己的孩子，走到哪都安心。 | G74: 生活能力，是最實用的教養。 | H74: 4 | K74: 品格 教養+1 | M74: 是 | N74: M6 | O74: m6.json
A75: LT_C071 | B75: CULTIVATE | C75: 住 | D75: 教養 | E75: 一起整理房間的習慣 | F75: 收拾自己的空間，也收拾責任感。 | G75: 秩序感，是從自己的抽屜開始的。 | H75: 0 | I75: 1 | K75: 品格 教養+1 | M75: 是 | N75: M6 | O75: m6.json
A76: LT_C072 | B76: CULTIVATE | C76: 育樂 | D76: 教養 | E76: 陪孩子面對一次失敗 | F76: 名次不好那天，你只是陪著。 | G76: 接住失敗的孩子，才敢再嘗試。 | H76: 0 | K76: 品格 教養+1 | M76: 是 | N76: M6 | O76: m6.json
A77: LT_C073 | B77: CULTIVATE | C77: 行 | D77: 教養 | E77: 一起規劃家庭出遊 | F77: 讓孩子查資料、抓預算、排行程。 | G77: 把決定權交出去，能力就長出來。 | H77: 8 | K77: 品格 教養+1 | M77: 是 | N77: M6 | O77: m6.json
A78: LT_C074 | B78: CULTIVATE | C78: 育樂 | D78: 教養 | E78: 固定的家庭會議 | F78: 每週半小時，孩子也有發言權。 | G78: 被聽見的孩子，比較願意溝通。 | H78: 0 | K78: 品格 教養+1 | M78: 是 | N78: M6 | O78: m6.json
A79: LT_C075 | B79: CULTIVATE | C79: 孝親家庭 | D79: 孝親 | E79: 陪父母回老家走走 | F79: 車上那兩小時，聽了很多故事。 | G79: 有些話，只在路上才說得出口。 | H79: 6 | K79: 品格 孝親+1 | N79: M6 | O79: m6.json
A80: LT_C076 | B80: CULTIVATE | C80: 孝親家庭 | D80: 孝親 | E80: 替父母整理數位帳號 | F80: 密碼、常用 App、緊急聯絡，一次盤清。 | G80: 數位時代的孝順，是幫他們不被卡住。 | H80: 2 | K80: 品格 孝親+1 | N80: M6 | O80: m6.json
A81: LT_C077 | B81: CULTIVATE | C81: 孝親家庭 | D81: 孝親 | E81: 記錄父母的病史與用藥 | F81: 看診時拿得出來，醫生更好判斷。 | G81: 一份清單，可能省下一場誤診。 | H81: 1 | K81: 品格 孝親+1 | N81: M6 | O81: m6.json
A82: LT_C078 | B82: CULTIVATE | C82: 孝親家庭 | D82: 孝親 | E82: 固定的家庭視訊夜 | F82: 隔著螢幕，也把日子接在一起。 | G82: 距離不是問題，不聯絡才是。 | H82: 0 | I82: 1 | K82: 品格 孝親+1 | N82: M6 | O82: m6.json
A83: LT_C079 | B83: CULTIVATE | C83: 孝親家庭 | D83: 孝親 | E83: 替長輩安排定期健檢 | F83: 預約掛號、陪同、追蹤報告。 | G83: 早一步發現，就多一分從容。 | H83: 8 | K83: 品格 孝親+1 | N83: M6 | O83: m6.json
A84: LT_C080 | B84: CULTIVATE | C84: 孝親家庭 | D84: 孝親 | E84: 學做父母愛吃的家常菜 | F84: 那個味道，是家的座標。 | G84: 把記憶裡的味道傳下去。 | H84: 3 | K84: 品格 孝親+1 | N84: M6 | O84: m6.json
A85: LT_T001 | B85: TRIAL | C85: 行 | D85: 情緒 | E85: 高速公路上的別車 | F85: 對方切進來只差半個車身。 | G85: 路怒的代價不只罰款，還有被扣住的那段人生。 | L85: axis：TEMPER｜ threshold：2｜ above：你深呼吸放慢車速讓他先過，到家早忘了這事。｜ below：你逼車回敬被檢舉，吊扣駕照三個月全靠計程車。｜現金 -120 對象:自己（罰鍰與代步支出） | N85: M6 | O85: m6.json
A86: LT_T002 | B86: TRIAL | C86: 住 | D86: 情緒 | E86: 樓上漏水的談判 | F86: 天花板滴了三週，對方一直不回訊息。 | G86: 同一糾紛，用調解或用訴訟，差一個月的支出。 | L86: axis：TEMPER｜ threshold：1｜ above：你先蒐證再找調解委員會，兩次會面就談成分攤。｜現金 -15 對象:自己（訴訟費與修繕） below：你在群組公開叫罵，對方反告妨害名譽，兩邊請律師。｜現金 -90 對象:自己（訴訟費與修繕） | N86: M6 | O86: m6.json
A87: LT_T003 | B87: TRIAL | C87: 食 | D87: 情緒 | E87: 尾牙那桌的爭執 | F87: 酒過三巡，話開始不好聽了。 | G87: 情緒失控的帳單，通常隔天早上才寄到。 | L87: axis：TEMPER｜ threshold：1｜ above：你放下杯子先送同事回家，隔天大家都謝謝你。｜ below：推擠中打破店裡隔屏，做完筆錄後和解賠償。｜現金 -55 對象:自己（賠償與和解金） | N87: M6 | O87: m6.json
A88: LT_T004 | B88: TRIAL | C88: 衣 | D88: 情緒 | E88: 週年慶的購物車 | F88: 限時三小時，滿額再送。 | G88: 衝動購物的帳單會分十二期提醒你當時的心情。 | L88: axis：TEMPER｜ threshold：1｜ above：你把購物車放過一夜，隔天只留真正需要的兩件。｜現金 -12 對象:自己（衝動消費與循環利息） below：你刷了卡也刷了關係，為帳單跟家人冷戰兩週。｜現金 -58 對象:自己（衝動消費與循環利息） | N88: M6 | O88: m6.json
A89: LT_T005 | B89: TRIAL | C89: 育樂 | D89: 情緒 | E89: 線上遊戲的口角 | F89: 對方一句嘲諷，你手指懸在課金鍵上。 | G89: 為了爭一口氣課下去的金，事後最難解釋。 | L89: axis：TEMPER｜ threshold：1｜ above：你關掉遊戲去洗了個澡，回來已經無所謂了。｜ below：你連課三筆想壓過對方，帳單來時只剩懊悔。｜現金 -40 對象:自己（衝動課金） | N89: M6 | O89: m6.json
A90: LT_T006 | B90: TRIAL | C90: 行 | D90: 情緒 | E90: 停車位的爭執 | F90: 你先看到的位子，被硬插了進去。 | G90: 一個車位不值得賠上一整天與一身傷。 | L90: axis：TEMPER｜ threshold：2｜ above：你笑笑地再繞一圈，找到更近的位子。｜ below：雙方下車推擠，一個報警一個掛彩，各自賠償。｜現金 -70 對象:自己（和解與醫藥費） | N90: M6 | O90: m6.json
A91: LT_T007 | B91: TRIAL | C91: 住 | D91: 情緒 | E91: 裝潢糾紛的當面對質 | F91: 工班做壞了又不認帳。 | G91: 帶著情緒談判，通常只會讓成本更高。 | L91: axis：TEMPER｜ threshold：1｜ above：你冷靜出示合約與照片，對方同意重做。｜現金 -8 對象:自己（重做工程加價） below：你當場翻臉趕人，工程停擺又得重找師傅加價。｜現金 -65 對象:自己（重做工程加價） | N91: M6 | O91: m6.json
A92: LT_T008 | B92: TRIAL | C92: 食 | D92: 情緒 | E92: 外送遲到的客訴 | F92: 餐點冷了，App 又打不通。 | G92: 為小事動怒，賠掉的是自己一整晚的好心情。 | L92: axis：TEMPER｜ threshold：1｜ above：你平和申訴，平台退款還補了折價券。｜ below：你留一星怒評又打電話飆罵，最後什麼也沒改變。｜現金 -6 對象:自己（重買一餐） | N92: M6 | O92: m6.json
A93: LT_T009 | B93: TRIAL | C93: 行 | D93: 守法謹慎 | E93: 十字路口的擦撞 | F93: 綠燈起步，右側機車突然竄出。 | G93: 保險與謹慎是把大額尾部風險換成小額固定成本。 | L93: axis：PRUDENCE｜ threshold：1｜ above：你上過防禦駕駛、保險齊全，對方全責，只付免賠額。｜現金 -8 對象:自己（車禍維修與罰款） below：記錄器拍到你超速搶快，維修罰款和解一起來。｜現金 -75 對象:自己（車禍維修與罰款） | N93: M6 | O93: m6.json
A94: LT_T010 | B94: TRIAL | C94: 住 | D94: 守法謹慎 | E94: 頂樓加蓋被檢舉 | F94: 里長說有人拍照去投訴了。 | G94: 違規的成本從不是罰單本身，是拆除與重做。 | L94: axis：PRUDENCE｜ threshold：1｜ above：你當初就依規申請，只需補件與小額罰鍰。｜現金 -10 對象:自己（拆除與復原工程） below：未申請的加蓋被列管限期拆除，還得復原防水。｜現金 -95 對象:自己（拆除與復原工程） | N94: M6 | O94: m6.json
A95: LT_T011 | B95: TRIAL | C95: 住 | D95: 守法謹慎 | E95: 廚房的小火 | F95: 油鍋起火那三秒，時間過得很慢。 | G95: 火險保費一年幾千，沒保的那年可能是幾十萬。 | L95: axis：PRUDENCE｜ threshold：1｜ above：滅火器就在手邊、火險早保了，理賠後自付一點。｜現金 -14 對象:自己（修復工程） below：沒滅火器也沒保火險，整套廚具與天花板重做。｜現金 -110 對象:自己（修復工程） | N95: M6 | O95: m6.json
A96: LT_T012 | B96: TRIAL | C96: 食 | D96: 守法謹慎 | E96: 宴客後的腸胃炎 | F96: 冰箱深處那盒，你其實猶豫過。 | G96: 食安的疏忽會變成別人的醫藥費與你的信譽。 | L96: axis：PRUDENCE｜ threshold：1｜ above：你出門前檢查過每樣食材，過期的早丟了。｜ below：兩位朋友掛急診，你負擔醫藥費也失去一個週末。｜現金 -42 對象:自己（醫藥費與慰問） | N96: M6 | O96: m6.json
... A101: LT_T017 | B101: TRIAL | C101: 食 | D101: 守法謹慎 | E101: 保健食品的大單 | F101: 業務說買一年份最划算。 | G101: 恐懼行銷面前，證據比話術重要。 | L101: axis：PRUDENCE｜ threshold：1｜ above：你查了成分覺得沒必要，只買一小盒試。｜現金 -5 對象:自己（囤貨浪費） below：你被說動囤了一整年，吃兩個月就發現沒感覺。｜現金 -38 對象:自己（囤貨浪費） | N101: M6 | O101: m6.json
A102: LT_T018 | B102: TRIAL | C102: 育樂 | D102: 教養 | E102: 手機遊戲的帳單 | F102: 信用卡簡訊連響十七次。 | G102: 孩子的金錢觀是教出來的，不是等帳單來教。 | L102: axis：PARENTING｜ threshold：1｜ above：你們早約好每月遊戲預算，他自己停在額度內。｜現金 -3 對象:自己（遊戲儲值） below：半夜用你的卡課金，申訴不成，只能當昂貴一課。｜現金 -45 對象:自己（遊戲儲值） | M102: 是 | N102: M6 | O102: m6.json
A103: LT_T019 | B103: TRIAL | C103: 育樂 | D103: 教養 | E103: 深夜的一通電話 | F103: 派出所說，請家長來一趟。 | G103: 青春期的孩子需要陪伴，不是保證金。 | L103: axis：PARENTING｜ threshold：2｜ above：導師與你早有默契，孩子道歉並完成勞動服務。｜現金 -10 對象:自己（保證金與賠償） below：對方要求賠償，你先繳保證金，還有幾次調解要跑。｜現金 -60 對象:自己（保證金與賠償） | M103: 是 | N103: M6 | O103: m6.json
A104: LT_T020 | B104: TRIAL | C104: 育樂 | D104: 教養 | E104: 他說不想去學校了 | F104: 連續第五天，他把棉被拉過頭。 | G104: 及早介入的輔導成本，遠低於長期缺課的代價。 | L104: axis：PARENTING｜ threshold：1｜ above：你請半天假陪他去談，導師與輔導老師接住這事。｜現金 -8 對象:自己（諮商與課輔） below：拖了兩個月才處理，需自費諮商與課業補救。｜現金 -52 對象:自己（諮商與課輔） | M104: 是 | N104: M6 | O104: m6.json
A105: LT_T021 | B105: TRIAL | C105: 食 | D105: 教養 | E105: 偏食引發的健康警訊 | F105: 健檢報告上的紅字讓你心頭一驚。 | G105: 飲食習慣是童年養成的，改起來要趁早。 | L105: axis：PARENTING｜ threshold：1｜ above：你們早就一起調整三餐，複檢一切正常。｜現金 -6 對象:自己（就醫與飲食調整） below：長期外食與含糖飲料，得長期追蹤與調理。｜現金 -40 對象:自己（就醫與飲食調整） | M105: 是 | N105: M6 | O105: m6.json
...

Sheet 人生商城
A1: FinFlow 內容盤點｜人生商城
A2: MALL 26 件。規則：只在自己回合買、每輪 1 件、同件 3 輪冷卻、重複購買幸福感遞減。「月薪倍數」有值者價格＝月薪×倍數（無薪時用固定價）。金額單位＝千元。
A4: id | B4: 分組 | C4: 圖示 | D4: 商品 | E4: 一次費用 | F4: 月薪倍數 | G4: 年繳保費 | H4: 每月支出 | I4: 幸福感 | J4: 一局限一次 | K4: 可續約 | L4: 需要小孩 | M4: 醫療險 | N4: 住宅火險 | O4: 人脈 | P4: 品格軸 | Q4: 停走 | R4: 成功機率 | S4: 成功效果 | T4: 失敗效果 | U4: 比賽獎項 | V4: 旗標 | W4: 備註 | X4: 情境 | Y4: 教育註記 | Z4: 標籤 | AA4: 模組 | AB4: 來源檔
A5: ML_EDU1 | B5: 進修學習 | C5: 💻 | D5: 線上專業課程 | E5: 40 | I5: 1 | R5: 0.45 | S5: {"salaryMult": 1.05, "label": "課程學以致用，接到加給"} | T5: 沒有直接反映在薪水上，但你學到東西了 | X5: 每週兩晚，三個月結業。 | Y5: 投資自己不保證加薪，但長期期望值為正——關鍵是持續，不是一次。 | Z5: career | AB5: mall.json
A6: ML_EDU2 | B6: 進修學習 | C6: 📜 | D6: 專業證照班 | E6: 120 | I6: 1 | Q6: 1 | R6: 0.55 | S6: {"salaryMult": 1.12, "label": "考取證照，薪資調整"} | T6: 這次沒過，明年再來 | X6: 週末全天班，考試在三個月後。 | Y6: 證照＝用今天的現金與時間，換未來每個月的加薪。 | Z6: career | AB6: mall.json
A7: ML_EDU3 | B7: 進修學習 | C7: 🗣️ | D7: 語言進修班 | E7: 60 | I7: 1 | R7: 0.4 | S7: {"salaryMult": 1.06, "label": "外語加給"} | T7: 還沒到能加給的程度 | X7: 外派缺一直開，但你差一張成績單。 | Y7: 語言像複利，短期看不出來，五年後差很多。 | Z7: career | AB7: mall.json
A8: ML_HEA1 | B8: 健康身心 | C8: 🏋️ | D8: 健身房年約 | E8: 12 | H8: 3 | I8: 2 | K8: 是 | V8: fit（24 輪） | W8: 往後 24 輪，醫療與意外類支出減 30% | X8: 辦卡容易，去了才算數。 | Y8: 健康是最被低估的資產：省下的醫療費不會出現在報表上，但一直都在。 | Z8: health | AB8: mall.json
A9: ML_HEA2 | B9: 健康身心 | C9: 🩺 | D9: 高階健康檢查 | E9: 25 | I9: 1 | K9: 是 | V9: checked（12 輪） | W9: 往後 12 輪，醫療類支出減 30% | X9: 一年一次，早發現早處理。 | Y9: 預防性支出是「用小錢買掉尾端風險」，跟保險是同一個道理。 | Z9: health | AB9: mall.json
A10: ML_INS1 | B10: 風險移轉 | C10: 🛡️ | D10: 醫療＋意外險 | H10: 4.5 | I10: 1 | M10: 是 | W10: 投保期間，醫療與意外類的一次性支出理賠 60% | X10: 平常沒感覺，出事那天才知道差別。 | Y10: 保險不是投資，是把「賠不起的風險」用固定小錢換成確定成本。 | Z10: insurance | AB10: mall.json
A11: ML_VIR1 | B11: 人情品格 | C11: 🧧 | D11: 包紅包（親友喜事） | E11: 12 | I11: 1 | P11: 孝親 | X11: 人情這件事，來往才會在。 | Y11: 人情支出不是浪費，但要有預算——沒編預算的人情最傷現金流。 | Z11: social | AB11: mall.json
A12: ML_VIR2 | B12: 人情品格 | C12: 👴 | D12: 孝親金加碼 | E12: 30 | I12: 2 | P12: 孝親 | X12: 這個月多包一點回家。 | Y12: 孝親金要放進固定支出裡編列，才不會月底才發現超支。 | Z12: social | AB12: mall.json
A13: ML_VIR3 | B13: 人情品格 | C13: 🤲 | D13: 公益定期捐款 | E13: 6 | H13: 1.5 | I13: 2 | P13: 情緒 | X13: 每個月一點點，不痛但持續。 | Y13: 能穩定給出去的人，通常先把自己的現金流管好了。 | Z13: social | AB13: mall.json
A14: ML_VIR4 | B14: 人情品格 | C14: 📚 | D14: 孩子的才藝課 | E14: 8 | H14: 2 | I14: 2 | L14: 是 | P14: 教養 | X14: 他說想學，你說好。 | Y14: 教育支出是長期投入，先確認每月現金流撐得住再報名。 | Z14: family | AB14: mall.json
A15: ML_CMP1 | B15: 挑戰比賽 | C15: 🏃 | D15: 報名城市馬拉松 | E15: 8 | I15: 2 | U15: [{"min": 5, "prize": 15, "label": "分組前段完賽，拿到獎金"}, {"min": 3, "prize": 5, "label": "順利完賽，領到完賽禮"}, {"min": 1, "prize": 0, "label": "中途退賽，下次再來"}] | X15: 報名費不貴，訓練才貴。 | Y15: 設定可達成的目標並完成它，是紀律的練習——理財也一樣。 | Z15: health | AB15: mall.json
A16: ML_CMP2 | B16: 挑戰比賽 | C16: 🚀 | D16: 創業競賽報名 | E16: 25 | I16: 1 | U16: [{"min": 6, "prize": 150, "label": "首獎！獎金入帳"}, {"min": 4, "prize": 40, "label": "佳作，拿到小額獎金"}, {"min": 1, "prize": 0, "label": "未入圍，評審給了建議"}] | X16: 一份計畫書，一場八分鐘簡報。 | Y16: 獎金是彩蛋，真正的收穫是把想法算成數字的過程。 | Z16: career | AB16: mall.json
A17: ML_CMP3 | B17: 挑戰比賽 | C17: 📈 | D17: 投資模擬賽 | E17: 15 | I17: 1 | U17: [{"min": 5, "prize": 40, "label": "績效前段班，獎金入帳"}, {"min": 1, "prize": 0, "label": "這季操作不理想，學到教訓"}] | X17: 用假錢比績效，賽制三個月。 | Y17: 模擬賽會鼓勵你冒險，真錢不會——別把賽場習慣帶進真帳戶。 | Z17: equity | AB17: mall.json
A18: ML_EDU4 | B18: 進修學習 | C18: 🎓 | D18: 海外碩士留學（一年衝刺） | E18: 900 | I18: 2 | J18: 是 | O18: 是 | Q18: 2 | R18: 0.7 | S18: {"salaryMult": 1.35, "label": "學成歸國，身價不同"} | T18: 學位沒直接反映在薪水上，但視野回不去了 | W18: 校友與同學會成為你的人脈——解鎖「特殊機會」 | X18: 辭掉工作出去一年，回來的是不一樣的自己。 | Y18: 留學是人生最大的單筆自我投資之一：學費＋機會成本都要算進去。 | Z18: career | AB18: mall.json
A19: ML_EDU5 | B19: 進修學習 | C19: ✈️ | D19: 海外短期進修（三個月） | E19: 220 | I19: 1 | Q19: 1 | R19: 0.5 | S19: {"salaryMult": 1.1, "label": "進修成果被看見"} | T19: 履歷多一行，薪水暫時沒動 | X19: 帶著筆電和一卡皮箱，去上三個月的課。 | Y19: 短期進修風險低、回報也溫和——適合試水溫再決定要不要重押。 | Z19: career | AB19: mall.json
A20: ML_LUX1 | B20: 尊榮享受 | C20: ⛳ | D20: 高爾夫俱樂部會員卡 | E20: 300 | H20: 5 | I20: 2 | X20: 球敘上談成的生意，比會議室多。 | Y20: 人脈場也是支出場：會籍是資產還是負債，取決於你帶回什麼。 | Z20: social、luxury | AB20: mall.json
A21: ML_LUX2 | B21: 尊榮享受 | C21: 🎿 | D21: 海外滑雪度假年票 | E21: 150 | I21: 2 | X21: 每年冬天固定消失兩週，朋友都知道去哪找你。 | Y21: 為體驗付費是好的消費——前提是現金流付得起，不是卡付得起。 | Z21: travel、luxury | AB21: mall.json
A22: ML_LUX3 | B22: 尊榮享受 | C22: 💳 | D22: 頂級信用卡黑卡年費 | E22: 60 | H22: 2 | I22: 1 | X22: 機場貴賓室隨便進，帳單也隨便來。 | Y22: 年費買的是禮遇與虛榮的匯率——換算成你的時薪再決定。 | Z22: luxury | AB22: mall.json
A23: ML_CMP4 | B23: 挑戰比賽 | C23: 🤖 | D23: AI 程式設計大賽 | E23: 10 | I23: 2 | U23: [{"min": 5, "prize": 60, "label": "奪冠！獎金與offer一起來"}, {"min": 3, "prize": 20, "label": "入圍決賽，拿到佳作獎金"}, {"min": 1, "prize": 0, "label": "沒得名，但作品集厚了一頁"}] | X23: 48 小時黑客松，披薩和咖啡因無限供應。 | Y23: 技能型比賽的獎金是其次，作品集與人脈才是複利。 | Z23: career | AB23: mall.json
A24: ML_CMP5 | B24: 挑戰比賽 | C24: 🏐 | D24: 大專排球聯賽（社會組） | E24: 6 | I24: 2 | U24: [{"min": 5, "prize": 12, "label": "打進四強，抱回獎金"}, {"min": 3, "prize": 4, "label": "小組出線，拿到參賽獎勵"}, {"min": 1, "prize": 0, "label": "一輪遊，明年再來"}] | X24: 每週練球兩晚，比賽那天全隊都到了。 | Y24: 團隊運動買不到，只能練——身體與人際都是資產。 | Z24: health、social | AB24: mall.json
A25: ML_EDU6 | B25: 進修學習 | C25: 🎓 | D25: EMBA 在職專班（兩年） | E25: 560 | I25: 1 | J25: 是 | O25: 是 | R25: 0.6 | S25: {"salaryMult": 1.18, "label": "論文題目變成公司專案，升遷加薪"} | T25: 學位拿到了，但職位還沒動——人脈要時間發酵 | W25: 解鎖「特殊機會」牌堆（人脈才進得去的案子） | X25: 週末上課，同學一半是老闆。 | Y25: EMBA 的學費裡有一大半買的是同學名單——這是最誠實也最貴的人脈投資。 | Z25: career、network | AB25: mall.json
A26: ML_INS2 | B26: 風險移轉 | C26: 🏠 | D26: 住宅火險＋地震基本保險 | G26: 18 | I26: 0 | N26: 是 | W26: 年繳、每年自動續約；房產修繕與天災損失理賠 50% | X26: 銀行說貸款一定要保，你才第一次認真看條款。 | Y26: 產險是年繳、自動續約——方便到你會忘記它一直在扣錢。記得每年重新檢視保額。 | Z26: insurance | AB26: mall.json
A27: ML_VIR5 | B27: 人情品格 | C27: 🙏 | D27: 安太座 | E27: 100 | F27: 1.5 | I27: 3 | J27: 否 | X27: 廟公貼上紅紙，老婆看著收據說「今年安心了」。Happy wife, happy life. | Y27: 有些支出買的不是資產，是家裡的安穩與笑容——這筆帳不會出現在報酬率裡。 | Z27: family | AB27: mall.json
A28: ML_HEA3 | B28: 健康身心 | C28: 🦷 | D28: 小孩牙齒矯正 | E28: 150 | I28: 2 | J28: 是 | L28: 是 | X28: 為了孩子一生的自信笑容，這筆年度預算省不得。 | Y28: 醫療健康支出往往是一次性大額負擔，平時的緊急預備金就是為了這刻而存在。 | Z28: medical、family | AB28: mall.json
A29: ML_LUX4 | B29: 尊榮享受 | C29: 🛥️ | D29: 遊艇俱樂部會籍 | E29: 500 | H29: 8 | I29: 2 | J29: 否 | X29: 迎風出海的頂級社交圈，碼頭泊位與年度保養也是頂級開銷。 | Y29: 頂級資產的入手價只是門票，每個月雷打不動的泊位與維護費才是現金流黑洞。 | Z29: luxury | AB29: mall.json
A30: ML_LUX5 | B30: 尊榮享受 | C30: 💳 | D30: 好市多 Costco 頂級黑鑽會員 | E30: 3 | H30: 0 | I30: 1 | J30: 否 | X30: 推著滿載牛肉與生活用品的推車，結帳時享受 2% 尊榮回饋感。 | Y30: 會員費買的是批發採購的單價優勢，但要小心在大包裝誘惑下買了過多不需要的消耗品。 | Z30: shopping | AB30: mall.json

Sheet 學習-技能
A1: FinFlow 內容盤點｜學習-技能
A2: SKILL 18 種（M8）。每局抽 6 張進場（抽到高階會把先修一起帶進來）。主動進修多花 1 輪；被動取得學費 7 折。金額單位＝千元。
A4: id | B4: 技能 | C4: 階級 | D4: 家族 | E4: 學費 | F4: 學習期間月費 | G4: 所需輪數 | H4: 會過時 | I4: 先修技能 | J4: 可轉職 | K4: 功能說明 | L4: 情境 | M4: 教育註記 | N4: 模組 | O4: 來源檔
A5: SKL_DRIVE | B5: 考取駕照 | C5: MID | D5: MOBILITY | E5: 20 | F5: 0 | G5: 4 | H5: 否 | K5: 交通類：可能在需要機動性的場合派上用場 | L5: 住台北有捷運，考完三年沒摸過方向盤。 | M5: 有些準備的價值，要等機會出現那天才結算。 | N5: M8 | O5: skill.json
A6: SKL_SPANISH | B6: 西班牙語進修 | C6: MID | D6: LANGUAGE | E6: 25 | F6: 2 | G6: 6 | H6: 否 | K6: 語言類：可能在涉外場合派上用場 | L6: 每週兩晚，同事問你學這個要幹嘛。 | M6: 語言打開的門，你不會事先知道門後有什麼。 | N6: M8 | O6: skill.json
A7: SKL_PLUMB | B7: 基礎水電 | C7: SMALL | D7: HANDS | E7: 15 | F7: 0 | G7: 3 | H7: 是 | K7: 手作類：可能在需要修繕的場合派上用場 | L7: 報名時家人笑：又不是要當師傅。 | M7: 會自己動手的人，維護成本永遠比別人低。 | N7: M8 | O7: skill.json
A8: SKL_CPR | B8: 急救 CPR | C8: SMALL | D8: SAFETY | E8: 8 | F8: 0 | G8: 2 | H8: 否 | K8: 安全類：可能在有人出事的場合派上用場 | L8: 一個週末的課，發完證書就丟抽屜。 | M8: 有些學習的回報不是錢，是那天你能不能站出來。 | N8: M8 | O8: skill.json
A9: SKL_PRESENT | B9: 簡報與說故事 | C9: MID | D9: COMMUNICATION | E9: 18 | F9: 0 | G9: 4 | H9: 否 | K9: 表達類：可能在需要說服別人的場合派上用場 | L9: 同事都說「內容好就好，誰在乎投影片」。 | M9: 好東西講不清楚，等於沒有。 | N9: M8 | O9: skill.json
A10: SKL_BOOK | B10: 記帳與看財報 | C10: MID | D10: FINANCE | E10: 20 | F10: 0 | G10: 4 | H10: 否 | K10: 財務類：可能在評估一門生意時派上用場 | L10: 上完課才發現自己以前根本沒在管錢。 | M10: 看得懂數字的人，比較不容易被數字騙。 | N10: M8 | O10: skill.json
A11: SKL_NEGO | B11: 談判與溝通 | C11: MID | D11: COMMUNICATION | E11: 18 | F11: 0 | G11: 4 | H11: 否 | K11: 表達類：可能在議價或交易的場合派上用場 | L11: 學費不便宜，上完好像也沒變得比較會吵架。 | M11: 談判不是把對方壓下去，是找到雙方都能走的路。 | N11: M8 | O11: skill.json
A12: SKL_LAW | B12: 法律常識 | C12: MID | D12: FINANCE | E12: 22 | F12: 0 | G12: 4 | H12: 是 | K12: 財務類：可能在遇到糾紛或可疑提案時派上用場 | L12: 學的時候想：我這輩子又不會上法院。 | M12: 不懂規則的人，最容易在規則裡吃虧。 | N12: M8 | O12: skill.json
A13: SKL_CODE | B13: 程式與自動化 | C13: MID | D13: TECH | E13: 30 | F13: 0 | G13: 6 | H13: 是 | K13: 技術類：可能在職涯轉折時派上用場（技術會過時，需要持續更新） | L13: 半夜自學，同事覺得你很無聊。 | M13: 技術是最快增值、也是折舊最快的資產。 | N13: M8 | O13: skill.json
A14: SKL_SWIM | B14: 學會游泳 | C14: SMALL | D14: SAFETY | E14: 10 | F14: 0 | G14: 3 | H14: 否 | K14: 安全類：可能在親水活動的場合派上用場 | L14: 每次去海邊都只能坐在岸上顧包包。 | M14: 有些能力，一輩子只需要用到一次，但那一次無可取代。 | N14: M8 | O14: skill.json
A15: SKL_PHOTO | B15: 攝影 | C15: SMALL | D15: CREATIVE | E15: 15 | F15: 0 | G15: 3 | H15: 否 | K15: 創作類：可能在需要留下紀錄的場合派上用場 | L15: 買了相機，拍完三次貓就放著。 | M15: 一項不務正業的技能，有時會在最需要的那天變成正業。 | N15: M8 | O15: skill.json
A16: SKL_CAR_FOOD | B16: 餐飲創業養成班 | C16: LARGE | D16: CAREER | E16: 55 | F16: 2 | G16: 6 | H16: 否 | J16: 是 | K16: 你有沒有想過，如果哪天不做現在這行了，還能靠什麼吃飯？ | L16: 每週兩晚在中央廚房，回家滿身油煙味。 | M16: 第二專長不是為了馬上換工作，是為了讓你在被迫換的時候還有得選。 | O16: skill.json
A17: SKL_CAR_DATA | B17: 資料分析轉職營 | C17: LARGE | D17: CAREER | E17: 48 | F17: 2 | G17: 6 | H17: 是 | J17: 是 | K17: 你有沒有想過，如果哪天不做現在這行了，還能靠什麼吃飯？ | L17: 六個月的線上課，最後要交一份真實資料的分析報告。 | M17: 技術類的第二專長回報快，但也是最會過時的那一種。 | O17: skill.json
A18: SKL_CAR_PLUMB | B18: 水電技術士證照班 | C18: LARGE | D18: CAREER | E18: 40 | F18: 1 | G18: 6 | H18: 是 | J18: 是 | K18: 你有沒有想過，如果哪天不做現在這行了，還能靠什麼吃飯？ | L18: 術科考場在職訓中心，考官盯著你接線。 | M18: 有牌的手藝在景氣壞的時候特別值錢——因為壞掉的東西不會等景氣。 | O18: skill.json
A19: SKL_CARPENTRY | B19: 木作與居家修繕 | C19: MID | D19: HANDS | E19: 25 | F19: 0 | G19: 4 | H19: 否 | K19: 手作類：自己動手把空間變好，可能在跟房子有關的地方派上用場 | L19: 週末在社區大學的木工教室，鋸子和砂紙。 | M19: 同樣一間房，有人租不掉，有人租得又快又好——差別常常在願不願意自己動手。 | O19: skill.json
A20: SKL_CPA_AUDIT | B20: 高階審計與財務分析 | C20: HIGH | D20: FINANCE | E20: 45 | F20: 0 | G20: 4 | H20: 否 | I20: SKL_BOOK | K20: 功能：解鎖獨立董事資格、在弊案爆發前收到審計警報並及時辭任避險。 | L20: 看透財報字裡行間的漏洞與做帳痕跡，一眼識破假帳黑洞。 | M20: 審計專業不只用來評估投資價值，更是避開偽裝吸金與假帳地雷的最強盾牌。 | N20: M8 | O20: skill.json
A21: SKL_GOV_LEGAL | B21: 公司法規與合規治理 | C21: HIGH | D21: LEGAL | E21: 40 | F21: 0 | G21: 4 | H21: 否 | I21: SKL_LAW | K21: 功能：解鎖獨立董事資格、免除連帶賠償、防範商業借名詐貸陷阱。 | L21: 在商業法規的灰色地帶守住紅線，明哲保身。 | M21: 懂法不是為了鑽漏洞，而是為資產築起防禦訴訟與董監連帶責任的防火牆。 | N21: M8 | O21: skill.json
A22: SKL_AI_ARCH | B22: AI 系統架構與應用 | C22: HIGH | D22: TECH | E22: 50 | F22: 0 | G22: 5 | H22: 否 | I22: SKL_CODE | K22: 功能：任何數位資產都以專業身分經營（門檻低、爆紅機率高）；科技類技能在產業變革事件中不會過時。 | L22: 將繁瑣工作自動化，打造自己的數位分身與長尾資產。 | M22: 掌握技術架構的人，在科技變革期能把外在變動轉化為持續性被動收入。 | N22: M8 | O22: skill.json

Sheet 學習-情境卡
A1: FinFlow 內容盤點｜學習-情境卡
A2: SKILL_GATE 12 張：第 12 輪後出現，每局 5 張，只抽「對應技能本局有進場」的情境。有技能兌現、沒有就錯過。
A4: id | B4: 標題 | C4: 需要技能 | D4: 情境 | E4: 教育註記 | F4: 有技能→敘述 | G4: 有技能→效果 | H4: 沒技能→敘述 | I4: 沒技能→效果 | J4: 需正在學習 | K4: 不得已有技能 | L4: 模組 | M4: 來源檔
A5: SKE_TEAMTRIP | B5: 部門團建要上山 | C5: SKL_DRIVE | D5: 主管在群組問：誰能開車載一車人？ | E5: 機會不會等你準備好，它只會問你準備好了沒。 | F5: 你開車，主管坐副駕。回程他說「下個案子你來帶」。 | G5: 薪水× ×1.1（被看見的機動力） | H5: 你搭別人的車坐在後座，一路聽他們在前座把下一季的分工聊完了。 | L5: M8 | M5: skill.json
A6: SKE_CLIENT | B6: 南美客戶下週來訪 | C6: SKL_SPANISH | D6: 老闆在會議上問：有沒有人會西班牙語？ | E6: 語言打開的門，你不會事先知道門後有什麼。 | F6: 你上桌翻譯兼聊足球，客戶指名你當窗口。 | G6: 薪水× ×1.15（外語加給）；幸福感 +1 | H6: 你在辦公室加班，看同事被帶去晚宴。 | L6: M8 | M6: skill.json
A7: SKE_HEATER | B7: 租客半夜打電話：熱水器不出熱水 | C7: SKL_PLUMB | D7: 電話那頭的聲音，聽起來已經在生氣了。 | E7: 會自己動手的人，維護成本永遠比別人低。 | F7: 你隔天自己換掉零件，順便跟租客混熟，續約談定。 | G7: 現金 -4 對象:自己（零件費） | H7: 叫師傅、急件加價，租客不爽，下期不續約。 | I7: 現金 -18 對象:自己（急件修繕與空租損失） | L7: M8 | M7: skill.json
A8: SKE_BANQUET | B8: 尾牙上，隔壁桌的長輩突然倒下 | C8: SKL_CPR | D8: 現場一片慌亂，有人喊「誰會急救」。 | E8: 有些學習的回報不是錢，是那天你能不能站出來。 | F8: 你壓胸壓到救護車來，人救回來了。全場沒有人記得那晚的菜色。 | G8: 幸福感 +3；品格 情緒+1 | H8: 你只能打 119，然後站在旁邊看著。那幾分鐘很長。 | L8: M8 | M8: skill.json
A9: SKE_BUDGET | B9: 年度預算會議 | C9: SKL_PRESENT | D9: 你的案子要跟另外兩個部門搶同一筆錢。 | E9: 好東西講不清楚，等於沒有。 | F9: 三頁講完，當場拍板。專案上線，年底獎金入袋。 | G9: 現金 +45 對象:自己（專案獎金） | H9: 你講了二十分鐘，主管低頭看手機。案子砍掉。 | L9: M8 | M9: skill.json
A10: SKE_FAKEBOOK | B10: 朋友邀你合資頂讓一間小吃攤 | C10: SKL_BOOK | D10: 「月營收很漂亮」，他把報表推到你面前。 | E10: 看得懂數字的人，比較不容易被數字騙。 | F10: 你翻了兩年流水，看出那營收是抓旺季推估的，笑著婉拒。 | H10: 你憑感覺投了，三個月後才發現淡季根本撐不住。 | I10: 現金 -70 對象:自己（看走眼的投資） | L10: M8 | M10: skill.json
A11: SKE_HAGGLE | B11: 店面成交前的最後一輪議價 | C11: SKL_NEGO | D11: 屋主說這個價已經是底線了。 | E11: 談判不是把對方壓下去，是找到雙方都能走的路。 | F11: 你看出他急著出手，多要了一成的裝修補貼。 | G11: 現金 +35 對象:自己（議價省下的錢） | H11: 你照開價成交，還覺得自己賺到。 | L11: M8 | M11: skill.json
A12: SKE_PONZI | B12: 老同學拿「保證月配 8%」的海外基金來找你 | C12: SKL_LAW | D12: 群組裡已經有五個人投了，他們都說很穩。 | E12: 不懂規則的人，最容易在規則裡吃虧。 | F12: 你當場看出是資金盤，還把群組其他人拉住。 | G12: 品格 守法謹慎+1 | H12: 你投了，半年後平台關站，群組解散得很安靜。 | I12: 現金 -200 對象:自己（資金盤losses） | L12: M8 | M12: skill.json
A13: SKE_AILAYOFF | B13: 公司導入 AI，部門要精簡一半人力 | C13: SKL_CODE | D13: 名單下週公布，辦公室很安靜。 | E13: 技術是最快增值、也是折舊最快的資產。 | F13: 你半夜自學的那些東西，讓你變成負責導入的那個人。 | G13: 薪水× ×1.25（轉型主力） | H13: 你在名單上。重新找工作花了一段時間。 | I13: 薪水× ×0.8（重新開始）；停走 2 輪（求職空窗） | L13: M8 | M13: skill.json
A14: SKE_WEDDING | B14: 好友婚禮前一週，攝影師落跑 | C14: SKL_PHOTO | D14: 新娘在電話那頭快哭了。 | E14: 一項不務正業的技能，有時會在最需要的那天變成正業。 | F14: 你頂上，成品出乎意料的好，賓客搶著要你名片。 | G14: 幸福感 +2；現金 +20 對象:自己（謝禮與後續案子） | H14: 大家用手機亂拍，那天的照片後來沒人再打開過。 | L14: M8 | M14: skill.json
A15: SKE_DROWNING | B15: 海邊玩水，姪子被浪捲離岸邊 | C15: SKL_SWIM | D15: 岸上的人都在喊，但沒有人下水。 | E15: 有些能力一輩子只用到一次，但那一次無可取代。 | F15: 你游過去把人拖回來。上岸後你們都在發抖。 | G15: 幸福感 +3；品格 情緒+1 | H15: 你只能在岸上大叫等救生員。那段時間長得像一輩子。 | L15: M8 | M15: skill.json
A16: SKE_CARCRASH | B16: 你被追撞，對方一口咬定是你煞太急 | C16: family:SAFETY | D16: 路口沒有目擊者，只有兩台車卡在那裡。 | E16: 遇到事情知道下一步該做什麼，本身就是一種保險。 | F16: 你冷靜拍照、報案、調閱行車記錄，肇責清楚。 | G16: 現金 -8 對象:自己（自付額） | H16: 現場沒拍沒報案，事後各說各話，肇責五五分。 | I16: 現金 -45 對象:自己（和解與修車） | L16: M8 | M16: skill.json

Sheet 學習-數位資產
A1: FinFlow 內容盤點｜學習-數位資產
A2: DIGITAL 6 種，每局 4 張，最多同時經營 3 個。有對應技能（或 AI 系統架構）＝專業：門檻 −1、爆紅 18%；沒有＝門檻 +2、爆紅 5%、50% 做白工。金額單位＝千元。
A4: id | B4: 標題 | C4: 對應技能 | D4: 建置費 | E4: 每月維護 | F4: 起飛門檻 | G4: 基礎月收入 | H4: 功能說明 | I4: 情境 | J4: 教育註記 | K4: 模組 | L4: 來源檔
A5: DIG_COURSE | B5: 線上課程：看懂一張財報 | C5: SKL_BOOK | D5: 30 | E5: 2 | F5: 4 | G5: 18 | H5: 要先看得懂財報，才教得了別人 | I5: 錄了十二支影片，剪到凌晨三點。 | J5: 課程上架那天不是終點，是長尾的第一天——沒人續作的課會被演算法忘記。 | K5: M8 | L5: skill.json
A6: DIG_YT_FIX | B6: YouTube 頻道：自己動手修 | C6: SKL_PLUMB | D6: 18 | E6: 2 | F6: 5 | G6: 16 | H6: 手上要真的有這門手藝，鏡頭騙不了人 | I6: 手機架在水槽旁邊，一邊修一邊講。 | J6: 實作型內容的長尾最長——因為壞掉的東西每年都會壞。 | K6: M8 | L6: skill.json
A7: DIG_PHOTO | B7: 圖庫授權與線上攝影課 | C7: SKL_PHOTO | D7: 22 | E7: 1 | F7: 6 | G7: 20 | H7: 要有拿得出手的作品 | I7: 上傳了四百張，前三個月賣出兩張。 | J7: 授權型收入前期幾乎是零，這是它勸退大多數人的方式。 | K7: M8 | L7: skill.json
A8: DIG_TOOL | B8: 自動化小工具訂閱制 | C8: SKL_CODE | D8: 35 | E8: 3 | F8: 4 | G8: 24 | H8: 要寫得出來，也要修得動 | I8: 本來只是自己要用，朋友問能不能也給他一份。 | J8: 訂閱制的甜蜜與詛咒是同一件事：你得一直維護它。 | K8: M8 | L8: skill.json
A9: DIG_NEWS | B9: 知識型電子報訂閱制 | C9: SKL_PRESENT | D9: 12 | E9: 2 | F9: 5 | G9: 15 | H9: 會講故事的人，才留得住讀者 | I9: 每週寄一封，寫的時候覺得沒人看，退訂的時候才知道有。 | J9: 訂閱制的收入看起來最像被動收入，其實最不被動——你得一直交稿。 | K9: M8 | L9: skill.json
A10: DIG_SPANISH | B10: 西語教學 Podcast | C10: SKL_SPANISH | D10: 15 | E10: 1 | F10: 5 | G10: 14 | H10: 要真的會講，不能只是會查 | I10: 每集十五分鐘，錄音室是你家衣櫃。 | J10: 語言內容的觀眾換得快，但每一批新學習者都會從第一集開始聽。 | K10: M8 | L10: skill.json

Sheet 徽章
A1: FinFlow 內容盤點｜徽章
A2: BADGE 29 種：復盤報告依 ns.badges.rules 的純函式判定。
A4: id | B4: 圖示 | C4: 徽章 | D4: 分組 | E4: 稀有度 | F4: 達成條件 | G4: 規則函式 | H4: 優先序 | I4: 互斥 | J4: 關聯 | K4: 來源檔
A5: BDG_READY | B5: 📖 | C5: 書到用時 | D5: 學習 | E5: COMMON | F5: 技能真的派上用場 5 次以上——你準備的東西，機會來的時候接得住。 | G5: ready | K5: skill.json
A6: BDG_TWOTRADE | B6: 🔧 | C6: 兩把刷子 | D6: 學習 | E6: COMMON | F6: 轉到不同產業的第二專長——整個產業一起倒的時候，你還有另一條路。 | G6: twoTrade | K6: skill.json
A7: BDG_LIFELONG | B7: 🎓 | C7: 終身學習者 | D7: 學習 | E7: COMMON | F7: 學成 4 項以上，而且一次都沒半途放棄。 | G7: lifelong | H7: 2 | I7: B、D、G、_、Q、U、I、T、T、E、R | K7: skill.json
A8: BDG_QUITTER | B8: 🥱 | C8: 半途而廢專家 | D8: 學習 | E8: COMMON | F8: 放棄學習 3 次以上——沉沒成本這門課，你上得很貴。 | G8: quitter | H8: 1 | I8: B、D、G、_、L、I、F、E、L、O、N、G | K8: skill.json
A9: BDG_WASTED | B9: 🌫 | C9: 白學了 | D9: 學習 | E9: COMMON | F9: 有 3 項以上技能整局沒用上。這不是你的錯——機會本來就不保證出現。 | G9: wasted | K9: skill.json
A10: BDG_LONGTAIL | B10: 📡 | C10: 長尾獵人 | D10: 數位 | E10: RARE | F10: 至少有一個數位資產真的起飛了。 | G10: longtail | K10: skill.json
A11: BDG_VIRAL | B11: 🚀 | C11: 演算法寵兒 | D11: 數位 | E11: RARE | F11: 做出一個爆紅的內容——享受它，但別把它當成常態。 | G11: viral | K11: skill.json
A12: BDG_GHOST | B12: 👻 | C12: 荒廢的頻道 | D12: 數位 | E12: RARE | F12: 有內容因為停更而歸零。長尾屬於持續的人。 | G12: ghost | K12: skill.json
A13: BDG_PRODIGY | B13: 🌟 | C13: 投資神童 | D13: 投資 | E13: COMMON | F13: 第 40 輪之前就達成財務自由。 | G13: prodigy | K13: skill.json
A14: BDG_KARATE | B14: 🥋 | C14: 空手道大師 | D14: 投資 | E14: COMMON | F14: 達成自由，而且身上一毛負債都沒有。 | G14: karate | H14: 2 | I14: B、D、G、_、L、E、V、E、R | K14: skill.json
A15: BDG_LEVER | B15: 🎚 | C15: 槓桿藝術家 | D15: 投資 | E15: COMMON | F15: 最高槓桿踩到 3 倍以上，還全身而退。 | G15: lever | H15: 1 | I15: B、D、G、_、K、A、R、A、T、E | K15: skill.json
A16: BDG_LANDLORD | B16: 🏘 | C16: 房產大亨 | D16: 投資 | E16: COMMON | F16: 同時持有 4 筆以上不動產。 | G16: landlord | K16: skill.json
A17: BDG_TYCOON | B17: 🏭 | C17: 事業王 | D17: 投資 | E17: COMMON | F17: 同時經營 5 門以上事業。 | G17: tycoon | K17: skill.json
A18: BDG_CASHFLOW | B18: 💧 | C18: 現金流獵人 | D18: 投資 | E18: COMMON | F18: 被動收入達到每月支出的兩倍以上。 | G18: cashflow | K18: skill.json
A19: BDG_TAKEPROFIT | B19: ✂️ | C19: 落袋為安 | D19: 投資 | E19: COMMON | F19: 主動停利 3 次以上——帳上的獲利不是你的錢，賣掉才是。 | G19: takeProfit | K19: skill.json
A20: BDG_NETWORK | B20: 🎓 | C20: 人脈存摺 | D20: 準備 | E20: COMMON | F20: 靠海外留學或 EMBA 打開了那扇門。 | G20: network | K20: skill.json
A21: BDG_INSURED | B21: 🛡 | C21: 有備無患 | D21: 準備 | E21: COMMON | F21: 醫療險與住宅火險同時在保——把賠不起的風險換成確定成本。 | G21: insured | K21: skill.json
A22: BDG_VIRTUE | B22: 🪷 | C22: 修養有成 | D22: 品格 | E22: COMMON | F22: 四個品格軸全部滿級。 | G22: virtue | K22: skill.json
A23: BDG_SAVED | B23: 🍀 | C23: 化險為夷 | D23: 品格 | E23: COMMON | F23: 品格在考驗中替你省下 300 以上。 | G23: saved | K23: skill.json
A24: BDG_CAT | B24: 🐈 | C24: 九命怪貓 | D24: 危機 | E24: RARE | F24: 從自由圈跌回兩次以上，最後還是沒倒。 | G24: cat | K24: skill.json
A25: BDG_ALMOST | B25: 😮‍💨 | C25: 差一步 | D25: 危機 | E25: RARE | F25: 三度逼近自由又跌回去——差的往往不是運氣，是水位。 | G25: almost | K25: skill.json
A26: BDG_TOP_LEARNER | B26: 🧠 | C26: 最會學的人 | D26: 頭銜 | E26: LEGEND | F26: 全場學成技能最多。 | G26: topLearner | J26: =TRUE() -> TRUE | K26: skill.json
A27: BDG_TOP_GAMBLER | B27: 🎲 | C27: 最敢賭的人 | D27: 頭銜 | E27: LEGEND | F27: 全場最高槓桿。 | G27: topGambler | J27: =TRUE() -> TRUE | K27: skill.json
A28: BDG_TOP_FREE | B28: 🕊 | C28: 最早自由的人 | D28: 頭銜 | E28: LEGEND | F28: 全場最早達成財務自由。 | G28: topFree | J28: =TRUE() -> TRUE | K28: skill.json
A29: BDG_TOP_FAMILY | B29: 💗 | C29: 最會照顧家人的人 | D29: 頭銜 | E29: LEGEND | F29: 全場幸福感最高。 | G29: topFamily | J29: =TRUE() -> TRUE | K29: skill.json
A30: BDG_TOP_BARGAIN | B30: 🧾 | C30: 最會撿便宜的人 | D30: 頭銜 | E30: LEGEND | F30: 全場靠技能省下最多。 | G30: topBargain | J30: =TRUE() -> TRUE | K30: skill.json
A31: BDG_TOP_SURVIVOR | B31: 🪨 | C31: 最慘但沒倒的人 | D31: 頭銜 | E31: LEGEND | F31: 全場淨值最低，但撐到最後沒有出局。 | G31: topSurvivor | J31: =TRUE() -> TRUE | K31: skill.json
A32: BDG_DIRECTOR_HERO | B32: 🚢 | C32: 人間清醒 | D32: 危機 | E32: RARE | F32: 在獨立董事弊案爆發前夕及時跳船請辭，全身而退免除上億民事求償。 | G32: directorHero | K32: skill.json
A33: BDG_SCAM_IMMUNE | B33: 🛡️ | C33: 鋼鐵避險王 | D33: 投資 | E33: RARE | F33: 運用財報審計或法規常識，識破並多次拒絕高息龐氏與假保本投資陷阱。 | G33: scamImmune | K33: skill.json

Sheet 盤面
A1: FinFlow 內容盤點｜盤面
A2: 內圈 24 格＋外圈 12 格的格子類型。
A4: 圈 | B4: 位置 | C4: 格子類型 | D4: 夢想類別 | E4: 其他
A5: 內圈 | B5: 0 | C5: PAYDAY | E5: {}
A6: 內圈 | B6: 1 | C6: OPPORTUNITY | E6: {}
A7: 內圈 | B7: 2 | C7: LIFESTYLE | E7: {}
A8: 內圈 | B8: 3 | C8: LIFE_EVENT | E8: {}
A9: 內圈 | B9: 4 | C9: PAYDAY | E9: {}
A10: 內圈 | B10: 5 | C10: MARKET | E10: {}
A11: 內圈 | B11: 6 | C11: OPPORTUNITY | E11: {}
A12: 內圈 | B12: 7 | C12: LIFE_EVENT | E12: {}
A13: 內圈 | B13: 8 | C13: PAYDAY | E13: {}
A14: 內圈 | B14: 9 | C14: OPPORTUNITY | E14: {}
A15: 內圈 | B15: 10 | C15: LIFESTYLE | E15: {}
A16: 內圈 | B16: 11 | C16: OPPORTUNITY | E16: {}
... A29: 外圈（夢想圈） | B29: 0 | C29: OPAYDAY | E29: {}
A30: 外圈（夢想圈） | B30: 1 | C30: SITE | D30: TASTE | E30: {}
A31: 外圈（夢想圈） | B31: 2 | C31: SITE | D31: SUMMIT | E31: {}
A32: 外圈（夢想圈） | B32: 3 | C32: OEVENT | E32: {}
A33: 外圈（夢想圈） | B33: 4 | C33: SITE | D33: VOYAGE | E33: {}
A34: 外圈（夢想圈） | B34: 5 | C34: SITE | D34: LEGACY | E34: {}
A35: 外圈（夢想圈） | B35: 6 | C35: OPAYDAY | E35: {}
A36: 外圈（夢想圈） | B36: 7 | C36: SITE | D36: SUMMIT | E36: {}
A37: 外圈（夢想圈） | B37: 8 | C37: SITE | D37: TASTE | E37: {}
A38: 外圈（夢想圈） | B38: 9 | C38: OEVENT | E38: {}
A39: 外圈（夢想圈） | B39: 10 | C39: SITE | D39: LEGACY | E39: {}
A40: 外圈（夢想圈） | B40: 11 | C40: SITE | D40: VOYAGE | E40: {}
